[
    {
        "intDurationHour": 11,
        "intOption": null,
        "intReviewStar": 0,
        "intReviewVisitor": 0,
        "intUsdCost": 5302,
        "strGuideLanguage": "русский,Português,中文,日本語,English,Italiano,Français,Español",
        "strImageUrl": "http://img.kkday.com/image/get/w_1024%2Cc_fit/s1.kkday.com/product_6688/20160314091832_5R8n7/jpg",
        "strIntroduction": "Full day excursion from Paris to the city of Reims and its region, known all over the world for the production of Champagne.",
        "strLocation": "France, Paris",
        "strOriginUrl": "https://www.kkday.com/en/product/6688",
        "strSource": "KKDAY",
        "strStyle": null,
        "strTitle": "Guided Tour of the Reims Champagne Region from Paris"
    },
    {
        "intDurationHour": 4,
        "intOption": null,
        "intReviewStar": 0,
        "intReviewVisitor": 0,
        "intUsdCost": 3593,
        "strGuideLanguage": "Deutsch,русский,Português,中文,日本語,English,Italiano,Français,Español",
        "strImageUrl": "http://img.kkday.com/image/get/w_1024%2Cc_fit/s1.kkday.com/product_8356/20160524132835_MUePX/jpg",
        "strIntroduction": "Have a Paris city tour and discover Paris major landmarks in a small group : Notre-Dame Cathedral, Montmartre district and climb up to the 2nd floor of the Eiffel Tower.",
        "strLocation": "France, Paris",
        "strOriginUrl": "https://www.kkday.com/en/product/8356",
        "strSource": "KKDAY",
        "strStyle": null,
        "strTitle": "Visit Notre-Dame Cathedral, Montmartre, Skip-the-line Eiffel Tower Access in a Small Group"
    },
    {
        "intDurationHour": 5,
        "intOption": null,
        "intReviewStar": 0,
        "intReviewVisitor": 0,
        "intUsdCost": 3075,
        "strGuideLanguage": "中文,English,Français",
        "strImageUrl": "http://img.kkday.com/image/get/w_1024%2Cc_fit/s1.kkday.com/product_8243/20160518081633_Eb40p/jpg",
        "strIntroduction": "You’ll find all the charm of a typical Provencal way of life mixed with an artistic environment that is still perceivable in these cities",
        "strLocation": "France, Avignon",
        "strOriginUrl": "https://www.kkday.com/en/product/8243",
        "strSource": "KKDAY",
        "strStyle": null,
        "strTitle": "The Van Gogh's tour"
    },
    {
        "intDurationHour": 2,
        "intOption": null,
        "intReviewStar": 0,
        "intReviewVisitor": 0,
        "intUsdCost": 4046,
        "strGuideLanguage": "English,Français",
        "strImageUrl": "http://img.kkday.com/image/get/w_1024%2Cc_fit/s1.kkday.com/product_7329/20160414060827_jaFkT/jpg",
        "strIntroduction": "Spend an evening at the Lido in Paris, enthralled by the Paris Merveilles show! Marvel at the precision and the energy of the dancing of the Bluebell Girls and the Lido Boys, and their stunning costumes, as you enjoy a half bottle of Champagne.",
        "strLocation": "France, Paris",
        "strOriginUrl": "https://www.kkday.com/en/product/7329",
        "strSource": "KKDAY",
        "strStyle": null,
        "strTitle": "Lido – Show and Champagne"
    },
    {
        "intDurationHour": 2,
        "intOption": null,
        "intReviewStar": 0,
        "intReviewVisitor": 0,
        "intUsdCost": 3625,
        "strGuideLanguage": "English",
        "strImageUrl": "http://img.kkday.com/image/get/w_1024%2Cc_fit/s1.kkday.com/product_5436/20151225041957_7bhLR/jpg",
        "strIntroduction": "Indulge yourself with an evening of sightseeing, dinner and music on the River Seine.",
        "strLocation": "France, Paris",
        "strOriginUrl": "https://www.kkday.com/en/product/5436",
        "strSource": "KKDAY",
        "strStyle": null,
        "strTitle": "Seine dinner cruise and city lights"
    },
    {
        "intDurationHour": 3,
        "intOption": null,
        "intReviewStar": 0,
        "intReviewVisitor": 0,
        "intUsdCost": 4059,
        "strGuideLanguage": "English,Français",
        "strImageUrl": "http://img.kkday.com/image/get/w_1024%2Cc_fit/s1.kkday.com/product_7750/20160430070625_IAqhY/jpg",
        "strIntroduction": "Come and cook 3 delicious desserts with Chef Frederic, who transmits to you his wonderful secrets in traditional or creative recipes.",
        "strLocation": "France, Paris",
        "strOriginUrl": "https://www.kkday.com/en/product/7750",
        "strSource": "KKDAY",
        "strStyle": null,
        "strTitle": "Dessert cooking class with Chef Frederic"
    },
    {
        "intDurationHour": 9,
        "intOption": null,
        "intReviewStar": 0,
        "intReviewVisitor": 0,
        "intUsdCost": 2946,
        "strGuideLanguage": "中文,English,Français",
        "strImageUrl": "http://img.kkday.com/image/get/w_1024%2Cc_fit/s1.kkday.com/product_8245/20160519095736_sGWg8/jpg",
        "strIntroduction": "Get ready for another French experience ! Histocal Bridge, Stunning Sightseeing and one of the most famous Wine Villages in France.",
        "strLocation": "France, Avignon",
        "strOriginUrl": "https://www.kkday.com/en/product/8245",
        "strSource": "KKDAY",
        "strStyle": null,
        "strTitle": "Great Vineyards and Roma heritage"
    },
    {
        "intDurationHour": 9,
        "intOption": null,
        "intReviewStar": 0,
        "intReviewVisitor": 0,
        "intUsdCost": 2379,
        "strGuideLanguage": "Deutsch,中文,English,Français,Español",
        "strImageUrl": "http://img.kkday.com/image/get/w_1024%2Cc_fit/s1.kkday.com/product_7188/20160408090054_ezARe/jpg",
        "strIntroduction": "Tour the wonderfully preserved medieval city of Provins",
        "strLocation": "France, Paris",
        "strOriginUrl": "https://www.kkday.com/en/product/7188",
        "strSource": "KKDAY",
        "strStyle": null,
        "strTitle": "1 Day Trip to Provins, Medieval City"
    },
    {
        "intDurationHour": 16,
        "intOption": null,
        "intReviewStar": 0,
        "intReviewVisitor": 0,
        "intUsdCost": 14745,
        "strGuideLanguage": "中文,English",
        "strImageUrl": "http://img.kkday.com/image/get/w_1024%2Cc_fit/s1.kkday.com/product_8668/20160604091411_8epIm/jpg",
        "strIntroduction": "Head off to discover the secrets of lavender in Provence! Admire the landscapes rich in colours and perfumes, full of history and traditions, which inspired many painters.",
        "strLocation": "France, Paris",
        "strOriginUrl": "https://www.kkday.com/en/product/8668",
        "strSource": "KKDAY",
        "strStyle": null,
        "strTitle": "Guided Daytrip in Provence: Villages in Lubéron and Lavender's Discovery - by TGV from Paris"
    },
    {
        "intDurationHour": 2,
        "intOption": null,
        "intReviewStar": 0,
        "intReviewVisitor": 0,
        "intUsdCost": 998,
        "strGuideLanguage": "Deutsch,русский,Português,中文,日本語,English,Italiano,Français,Español",
        "strImageUrl": "http://img.kkday.com/image/get/w_1024%2Cc_fit/s1.kkday.com/product_8277/20160525152746_xpScH/jpg",
        "strIntroduction": "Visit Paris by night in a double-decker bus. Discover the main monuments of Paris and the quarters, the bridges over the illuminated Seine river, the magic \"City of Lights\".",
        "strLocation": "France, Paris",
        "strOriginUrl": "https://www.kkday.com/en/product/8277",
        "strSource": "KKDAY",
        "strStyle": null,
        "strTitle": "Paris by Night: City Tour by Open Top bus"
    },
    {
        "intDurationHour": 4,
        "intOption": null,
        "intReviewStar": 0,
        "intReviewVisitor": 0,
        "intUsdCost": 3208,
        "strGuideLanguage": "English",
        "strImageUrl": "http://img.kkday.com/image/get/w_1024%2Cc_fit/s1.kkday.com/product_6970/20160325032843_TICQa/jpg",
        "strIntroduction": "Journey with us to the hill of marvellous Montmartre on one of our luxurious spacious coaches. Once there you will be able to continue to the top of the hill via cable-car or minibus, both of which offer a splendid view of the surrounding area near the Sacré-Coeur Basilica, one of the highest points in Paris.",
        "strLocation": "France, Paris",
        "strOriginUrl": "https://www.kkday.com/en/product/6970",
        "strSource": "KKDAY",
        "strStyle": null,
        "strTitle": "Musical Dinner at Montmartre"
    },
    {
        "intDurationHour": 7,
        "intOption": null,
        "intReviewStar": 0,
        "intReviewVisitor": 0,
        "intUsdCost": 8416,
        "strGuideLanguage": "English",
        "strImageUrl": "http://img.kkday.com/image/get/w_1024%2Cc_fit/s1.kkday.com/product_7208/20160408072533_SWwfr/jpg",
        "strIntroduction": "Experience the romance of Paris with an unforgettable night out that combines three of the top tours in the City of Lights.",
        "strLocation": "France, Paris",
        "strOriginUrl": "https://www.kkday.com/en/product/7208",
        "strSource": "KKDAY",
        "strStyle": null,
        "strTitle": "La Marina Dinner Cruise, Eiffel Tower and Lido Show"
    },
    {
        "intDurationHour": 12,
        "intOption": null,
        "intReviewStar": 0,
        "intReviewVisitor": 0,
        "intUsdCost": 906,
        "strGuideLanguage": "中文",
        "strImageUrl": "http://img.kkday.com/image/get/w_1024%2Cc_fit/s1.kkday.com/product_3328/20150831071000_Cv08m/jpg",
        "strIntroduction": "Welcome to La Vallée Village! Round trip transportation in a luxury air-conditioned bus or minibus.This unique village in France groups over a hundred prestigious fashion luxury brands.",
        "strLocation": "France, Paris",
        "strOriginUrl": "https://www.kkday.com/en/product/3328",
        "strSource": "KKDAY",
        "strStyle": null,
        "strTitle": "Shopping at La Vallée Village Outlet"
    },
    {
        "intDurationHour": 13,
        "intOption": null,
        "intReviewStar": 0,
        "intReviewVisitor": 0,
        "intUsdCost": 4807,
        "strGuideLanguage": "English,Français",
        "strImageUrl": "http://img.kkday.com/image/get/w_1024%2Cc_fit/s1.kkday.com/product_7210/20160409134024_qx9aQ/jpg",
        "strIntroduction": "Experience a guided tour to the 1916 Somme Battlefields and follow the route. This special itinerary of the “Circuit du Souvenir” will take you to the main battlefields and historical sites of the region.",
        "strLocation": "France, Paris",
        "strOriginUrl": "https://www.kkday.com/en/product/7210",
        "strSource": "KKDAY",
        "strStyle": null,
        "strTitle": "Guided Visit to The Somme Battlefields from Paris"
    },
    {
        "intDurationHour": 2,
        "intOption": null,
        "intReviewStar": 0,
        "intReviewVisitor": 0,
        "intUsdCost": 4273,
        "strGuideLanguage": "English,Français",
        "strImageUrl": "http://img.kkday.com/image/get/w_1024%2Cc_fit/s1.kkday.com/product_7828/20160520051108_lfzvr/jpg",
        "strIntroduction": "To improve your knowledge of french wines, we offer you a Master Class Tasting with a french oenological teacher. With a selection of 5 wines and the help of a tutorial, the teacher will provide you the differents skills!",
        "strLocation": "France, Paris",
        "strOriginUrl": "https://www.kkday.com/en/product/7828",
        "strSource": "KKDAY",
        "strStyle": null,
        "strTitle": "Private Wine masterclass : training to understand French wines"
    },
    {
        "intDurationHour": 4,
        "intOption": null,
        "intReviewStar": 0,
        "intReviewVisitor": 0,
        "intUsdCost": 5325,
        "strGuideLanguage": "Deutsch,русский,한국어,Português,中文,日本語,English,Italiano,Français,Español",
        "strImageUrl": "http://img.kkday.com/image/get/w_1024%2Cc_fit/s1.kkday.com/product_6905/20160323111259_3MuLA/jpg",
        "strIntroduction": "Make your night in Paris one to remember with this spectacular Seine river cruise and Moulin Rouge combination.",
        "strLocation": "France, Paris",
        "strOriginUrl": "https://www.kkday.com/en/product/6905",
        "strSource": "KKDAY",
        "strStyle": null,
        "strTitle": "Cruise and Moulin Rouge show with glass of Champagne"
    },
    {
        "intDurationHour": 1,
        "intOption": null,
        "intReviewStar": 0,
        "intReviewVisitor": 0,
        "intUsdCost": 822,
        "strGuideLanguage": "English,Français",
        "strImageUrl": "http://img.kkday.com/image/get/s1.kkday.com/product_7799/20160503103050_KCjzW/jpg",
        "strIntroduction": "Step behind the counter of a typical beautiful French bakery, a boulangerie, into the kitchen to watch a demonstration by the master baker of how a perfect baguette is made.",
        "strLocation": "France, Paris",
        "strOriginUrl": "https://www.kkday.com/en/product/7799",
        "strSource": "KKDAY",
        "strStyle": null,
        "strTitle": "Bakery Le Grenier à Pain"
    },
    {
        "intDurationHour": 5,
        "intOption": null,
        "intReviewStar": 0,
        "intReviewVisitor": 0,
        "intUsdCost": 4952,
        "strGuideLanguage": "English",
        "strImageUrl": "http://img.kkday.com/image/get/w_1024%2Cc_fit/s1.kkday.com/product_7860/20160504172108_tIHPE/jpg",
        "strIntroduction": "Meet at 9:15 am with Chef Dominique, our cooking teacher, in his apartment located at the border of the 11th and 20th district. You start with a morning market visit to purchase the requested produce for today's recipes.",
        "strLocation": "France, Paris",
        "strOriginUrl": "https://www.kkday.com/en/product/7860",
        "strSource": "KKDAY",
        "strStyle": null,
        "strTitle": "Market Visit and Cooking Class with Chef Dominique"
    },
    {
        "intDurationHour": 8,
        "intOption": null,
        "intReviewStar": 0,
        "intReviewVisitor": 0,
        "intUsdCost": 7768,
        "strGuideLanguage": "Deutsch,русский,한국어,Português,中文,日本語,English,Italiano,Français,Español",
        "strImageUrl": "http://img.kkday.com/image/get/w_1024%2Cc_fit/s1.kkday.com/product_8375/20160525041511_KkERq/jpg",
        "strIntroduction": "With your driver-guide, discover the major sites of Paris: Notre-Dame Cathedral, the Eiffel Tower and Montmartre and the Palace of Versaille.",
        "strLocation": "France, Paris",
        "strOriginUrl": "https://www.kkday.com/en/product/8375",
        "strSource": "KKDAY",
        "strStyle": null,
        "strTitle": "Day trip by Minivan : Paris Sightseeing, Eiffel Tower Lunch, Versailles"
    },
    {
        "intDurationHour": 96,
        "intOption": null,
        "intReviewStar": 0,
        "intReviewVisitor": 0,
        "intUsdCost": 5211,
        "strGuideLanguage": "中文,English",
        "strImageUrl": "http://img.kkday.com/image/get/w_1024%2Cc_fit/s1.kkday.com/product_6614/20160309074324_Er0Lv/jpg",
        "strIntroduction": "Hope to spend more days in Disneyland? Now it's your turn to make dreams come true! Come to plan a trip in Paris and enjoy the wonderful world of Disney.",
        "strLocation": "France, Paris",
        "strOriginUrl": "https://www.kkday.com/en/product/6614",
        "strSource": "KKDAY",
        "strStyle": null,
        "strTitle": "Disneyland Paris – 2 Parks"
    },
    {
        "intDurationHour": 2,
        "intOption": null,
        "intReviewStar": 5,
        "intReviewVisitor": 1,
        "intUsdCost": 809,
        "strGuideLanguage": "English",
        "strImageUrl": "http://img.kkday.com/image/get/w_1024%2Cc_fit/s1.kkday.com/product_1201/20150525102449_N846v/jpg",
        "strIntroduction": "Book your airport transfer from CDG Airport to your centrally located Paris hotel (postcode beginning with 75 only) !",
        "strLocation": "France, Paris",
        "strOriginUrl": "https://www.kkday.com/en/product/1201",
        "strSource": "KKDAY",
        "strStyle": null,
        "strTitle": "Paris Shared Arrival / Departure Transfer: CDG Airport"
    },
    {
        "intDurationHour": 1,
        "intOption": null,
        "intReviewStar": 0,
        "intReviewVisitor": 0,
        "intUsdCost": 815,
        "strGuideLanguage": "English,Français",
        "strImageUrl": "http://img.kkday.com/image/get/w_1024%2Cc_fit/s1.kkday.com/product_7802/20160504015256_9ilKG/jpg",
        "strIntroduction": "See firsthand the bustling kitchen of a famous macaron and chocolate shop in Paris. During this 1-hour behind-the-scenes tour, meet the head pastry chef and master chocolatier. Even better, taste different macarons and gourmet chocolates as you hear about the techniques that go into the world-renowned art of Parisian chocolate and macaron making.",
        "strLocation": "France, Paris",
        "strOriginUrl": "https://www.kkday.com/en/product/7802",
        "strSource": "KKDAY",
        "strStyle": null,
        "strTitle": "Gérard Mulot macaron and chocolate workshop"
    },
    {
        "intDurationHour": 3,
        "intOption": null,
        "intReviewStar": 0,
        "intReviewVisitor": 0,
        "intUsdCost": 4273,
        "strGuideLanguage": "English",
        "strImageUrl": "http://img.kkday.com/image/get/w_1024%2Cc_fit/s1.kkday.com/product_7243/20160415014441_ndFVH/jpg",
        "strIntroduction": "Admire the waterfront sights of Paris while enjoying a 3-course meal on this Seine River dinner cruise. Aboard a La Marina de Paris glass-enclosed boat, you’ll float along the river, admiring illuminated landmarks like the Eiffel Tower, Louvre and Notre Dame Cathedral. Pass under the Pont Neuf and other bridges while you sip French wine and Champagne. Unlike similar tours, this one includes transport for your convenience.",
        "strLocation": "France, Paris",
        "strOriginUrl": "https://www.kkday.com/en/product/7243",
        "strSource": "KKDAY",
        "strStyle": null,
        "strTitle": "Gourmet Dinner Cruise \"Saveurs Menu\" - La Marina with transport"
    },
    {
        "intDurationHour": 2,
        "intOption": null,
        "intReviewStar": 0,
        "intReviewVisitor": 0,
        "intUsdCost": 3884,
        "strGuideLanguage": "English",
        "strImageUrl": "http://img.kkday.com/image/get/w_1024%2Cc_fit/s1.kkday.com/product_7814/20160504062807_qVRRk/jpg",
        "strIntroduction": "Here's a cooking class with a difference - a rare opportunity to go behind the counter of a friendly family local Parisian bakery. We go into the kitchen to learn how to create French baguettes and croissants. Our teacher and demonstrator will be the baker himself.",
        "strLocation": "France, Paris",
        "strOriginUrl": "https://www.kkday.com/en/product/7814",
        "strSource": "KKDAY",
        "strStyle": null,
        "strTitle": "Bread-making class with a baker"
    },
    {
        "intDurationHour": 3,
        "intOption": null,
        "intReviewStar": 0,
        "intReviewVisitor": 0,
        "intUsdCost": 1353,
        "strGuideLanguage": "Deutsch,русский,中文,日本語,English,Italiano,Français,Español",
        "strImageUrl": "http://img.kkday.com/image/get/w_1024%2Cc_fit/s1.kkday.com/product_5550/20151228032610_QSPW1/jpg",
        "strIntroduction": "See what one of the most famous museums in the world has to offer with a tour of the Louvre Museum.",
        "strLocation": "France, Paris",
        "strOriginUrl": "https://www.kkday.com/en/product/5550",
        "strSource": "KKDAY",
        "strStyle": null,
        "strTitle": "Audio-Guided Visit of the Louvre Museum"
    },
    {
        "intDurationHour": 12,
        "intOption": null,
        "intReviewStar": 0,
        "intReviewVisitor": 0,
        "intUsdCost": 8464,
        "strGuideLanguage": "English",
        "strImageUrl": "http://img.kkday.com/image/get/w_1024%2Cc_fit/s1.kkday.com/product_6898/20160322074425_2SZGm/jpg",
        "strIntroduction": "Discover the tragedy of Verdun – a landscape scarred by one of WWI's bloodiest battles. The day tour covers the Fort and Ossuary of Douaumont, the Trench of Bayonets, the Meuse-Argonne US Cemetery, and the key battlefields among other places of interest.",
        "strLocation": "France, Paris",
        "strOriginUrl": "https://www.kkday.com/en/product/6898",
        "strSource": "KKDAY",
        "strStyle": null,
        "strTitle": "Verdun and Argonne battlefields"
    },
    {
        "intDurationHour": 12,
        "intOption": null,
        "intReviewStar": 0,
        "intReviewVisitor": 0,
        "intUsdCost": 8610,
        "strGuideLanguage": "English",
        "strImageUrl": "http://img.kkday.com/image/get/w_1024%2Cc_fit/s1.kkday.com/product_7843/20160504080626_fqXPl/jpg",
        "strIntroduction": "Pop a cork in France’s famous Champagne region on a full-day tour from Paris!",
        "strLocation": "France, Paris",
        "strOriginUrl": "https://www.kkday.com/en/product/7843",
        "strSource": "KKDAY",
        "strStyle": null,
        "strTitle": "A day in Champagne"
    },
    {
        "intDurationHour": 3,
        "intOption": null,
        "intReviewStar": 0,
        "intReviewVisitor": 0,
        "intUsdCost": 2858,
        "strGuideLanguage": "Português,English,Français",
        "strImageUrl": "http://img.kkday.com/image/get/s1.kkday.com/product_7815/20160510080240_mLeFJ/jpg",
        "strIntroduction": "A fun 3 hour fashion and style treat in the very heart of Paris, the world's Fashion Capital. Your friendly Parisian Fashionista guide will be your inspiration in unlocking the secrets of the Parisian sense of cool style and chic glamour.",
        "strLocation": "France, Paris",
        "strOriginUrl": "https://www.kkday.com/en/product/7815",
        "strSource": "KKDAY",
        "strStyle": null,
        "strTitle": "French Fashion, Fragrance and Fun"
    },
    {
        "intDurationHour": 4,
        "intOption": null,
        "intReviewStar": 0,
        "intReviewVisitor": 0,
        "intUsdCost": 1198,
        "strGuideLanguage": "Deutsch,English,Français",
        "strImageUrl": "http://img.kkday.com/image/get/w_1024%2Cc_fit/s1.kkday.com/product_4322/20151111083619_SEzv3/jpg",
        "strIntroduction": "A great way to begin your visit to Paris, you’ll see Notre Dame, the Louvre, the Eiffel Tower and loads more on this small-group bike tour.",
        "strLocation": "France, Paris",
        "strOriginUrl": "https://www.kkday.com/en/product/4322",
        "strSource": "KKDAY",
        "strStyle": null,
        "strTitle": "Best of Paris Bike Tour"
    },
    {
        "intDurationHour": 7,
        "intOption": null,
        "intReviewStar": 0,
        "intReviewVisitor": 0,
        "intUsdCost": 2331,
        "strGuideLanguage": "English",
        "strImageUrl": "http://img.kkday.com/image/get/w_1024%2Cc_fit/s1.kkday.com/product_6816/20160413092617_uAiXJ/jpg",
        "strIntroduction": "Fall in love with Paris with this full day tour that will take you to two of the most iconic sights in the city.",
        "strLocation": "France, Paris",
        "strOriginUrl": "https://www.kkday.com/en/product/6816",
        "strSource": "KKDAY",
        "strStyle": null,
        "strTitle": "The best of Paris, Musée d'Orsay and Notre Dame"
    },
    {
        "intDurationHour": 4,
        "intOption": null,
        "intReviewStar": 0,
        "intReviewVisitor": 0,
        "intUsdCost": 3602,
        "strGuideLanguage": "Deutsch,русский,한국어,Português,中文,日本語,English,Italiano,Français,Español",
        "strImageUrl": "http://img.kkday.com/image/get/w_1024%2Cc_fit/s1.kkday.com/product_8417/20160526070359_JpV4B/jpg",
        "strIntroduction": "After the cruise on the Seine River, we have booked you the best tables in the restaurant “Chez Clément” on the Champs-Élysées, one of the most fashionable of our capital city.",
        "strLocation": "France, Paris",
        "strOriginUrl": "https://www.kkday.com/en/product/8417",
        "strSource": "KKDAY",
        "strStyle": null,
        "strTitle": "Paris by Night : Cruise, City Tour, Dinner on the Champs Elysées"
    },
    {
        "intDurationHour": 13,
        "intOption": null,
        "intReviewStar": 0,
        "intReviewVisitor": 0,
        "intUsdCost": 6205,
        "strGuideLanguage": "Português,日本語,English,Français,Español",
        "strImageUrl": "http://img.kkday.com/image/get/w_1024%2Cc_fit/s1.kkday.com/product_6868/20160321085221_KgkJ8/jpg",
        "strIntroduction": "Step back in time with a tour to Bruges, one of the best preserved medieval towns in Europe.",
        "strLocation": "France, Paris",
        "strOriginUrl": "https://www.kkday.com/en/product/6868",
        "strSource": "KKDAY",
        "strStyle": null,
        "strTitle": "1 Day in Bruges from Paris"
    },
    {
        "intDurationHour": 2,
        "intOption": null,
        "intReviewStar": 0,
        "intReviewVisitor": 0,
        "intUsdCost": 2363,
        "strGuideLanguage": "English,Français",
        "strImageUrl": "http://img.kkday.com/image/get/w_1024%2Cc_fit/s1.kkday.com/product_7823/20160504045519_HDOFI/jpg",
        "strIntroduction": "Learn the art of French seduction on a 2-hour walking tour of Montmartre in Paris, the city of love and romance. You'll be introduced to the most charming secret locations where romance blossomed.",
        "strLocation": "France, Paris",
        "strOriginUrl": "https://www.kkday.com/en/product/7823",
        "strSource": "KKDAY",
        "strStyle": null,
        "strTitle": "The French art of seduction: love and romance in Montmartre"
    },
    {
        "intDurationHour": 2,
        "intOption": null,
        "intReviewStar": 0,
        "intReviewVisitor": 0,
        "intUsdCost": 1877,
        "strGuideLanguage": "日本語,English,Français",
        "strImageUrl": "http://img.kkday.com/image/get/w_1024%2Cc_fit/s1.kkday.com/product_7790/20160530114408_uQyVE/jpg",
        "strIntroduction": "Improve your French in Paris, the courses will be followed by a guided tour of the area.",
        "strLocation": "France, Paris",
        "strOriginUrl": "https://www.kkday.com/en/product/7790",
        "strSource": "KKDAY",
        "strStyle": null,
        "strTitle": "Conversation in French at Café de Flore"
    },
    {
        "intDurationHour": 3,
        "intOption": null,
        "intReviewStar": 0,
        "intReviewVisitor": 0,
        "intUsdCost": 3302,
        "strGuideLanguage": "English",
        "strImageUrl": "http://img.kkday.com/image/get/s1.kkday.com/product_7827/20160504055621_VJgyC/jpg",
        "strIntroduction": "We're going to let you into a secret! As a visitor to Paris, you would never know that behind many Parisian tree-lined wide boulevards, charming hidden passageways lie.",
        "strLocation": "France, Paris",
        "strOriginUrl": "https://www.kkday.com/en/product/7827",
        "strSource": "KKDAY",
        "strStyle": null,
        "strTitle": "Hidden Paris：Covered passages, secret shopping and gourmet treasures"
    },
    {
        "intDurationHour": 6,
        "intOption": null,
        "intReviewStar": 0,
        "intReviewVisitor": 0,
        "intUsdCost": 3334,
        "strGuideLanguage": "English",
        "strImageUrl": "http://img.kkday.com/image/get/w_1024%2Cc_fit/s1.kkday.com/product_7234/20160419064709_WiOdo/jpg",
        "strIntroduction": "Set off from our Central Paris agency at 6 pm for a magical evening at the Palace of Versailles and its gardens",
        "strLocation": "France, Paris",
        "strOriginUrl": "https://www.kkday.com/en/product/7234",
        "strSource": "KKDAY",
        "strStyle": null,
        "strTitle": "Royal Evening at Versailles: Night-time Fountain Extravaganza"
    },
    {
        "intDurationHour": 2,
        "intOption": null,
        "intReviewStar": 0,
        "intReviewVisitor": 0,
        "intUsdCost": 1382,
        "strGuideLanguage": "English",
        "strImageUrl": "http://img.kkday.com/image/get/w_1024%2Cc_fit/s1.kkday.com/product_6740/20160316100213_F3G0e/jpg",
        "strIntroduction": "Take a journey into the heart of medieval and Gothic Paris on a 2-hour guided tour. Visit the Notre Dame Cathedral, its famous bell towers, and climb 387 steps for a dramatic view over the entire city of Paris. Explore the beautiful Ile de la Cité.",
        "strLocation": "France, Paris",
        "strOriginUrl": "https://www.kkday.com/en/product/6740",
        "strSource": "KKDAY",
        "strStyle": null,
        "strTitle": "Notre Dame and Ile de la Cité Tour"
    },
    {
        "intDurationHour": 3,
        "intOption": null,
        "intReviewStar": 0,
        "intReviewVisitor": 0,
        "intUsdCost": 3140,
        "strGuideLanguage": "English",
        "strImageUrl": "http://img.kkday.com/image/get/s1.kkday.com/product_7133/20160401092752_uh4LO/jpg",
        "strIntroduction": "What pairs magnificently with art? Wine, of course. On this one-of-a-kind tour, you can get the best of both.",
        "strLocation": "France, Paris",
        "strOriginUrl": "https://www.kkday.com/en/product/7133",
        "strSource": "KKDAY",
        "strStyle": null,
        "strTitle": "Special Offer - Louvre Masterpieces and Wine Bottling Experience -20%"
    },
    {
        "intDurationHour": 72,
        "intOption": null,
        "intReviewStar": 0,
        "intReviewVisitor": 0,
        "intUsdCost": 1813,
        "strGuideLanguage": "Deutsch,русский,Português,中文,日本語,English,Italiano,Français,Español",
        "strImageUrl": "http://img.kkday.com/image/get/w_1024%2Cc_fit/s1.kkday.com/product_8349/20160524092504_vA9F0/jpg",
        "strIntroduction": "This three-day pass allows you to discover Paris by Open Tour bus and Batobus boat at your own pace. Your unlimited three-day pass gives you the freedom to discover Paris and enjoy commentary about Paris's key monuments.",
        "strLocation": "France, Paris",
        "strOriginUrl": "https://www.kkday.com/en/product/8349",
        "strSource": "KKDAY",
        "strStyle": null,
        "strTitle": "3 Day Hop on Hop off Bus and Boat Pass"
    },
    {
        "intDurationHour": 5,
        "intOption": null,
        "intReviewStar": 0,
        "intReviewVisitor": 0,
        "intUsdCost": 6506,
        "strGuideLanguage": "Português,English,Français,Español",
        "strImageUrl": "http://img.kkday.com/image/get/w_1024%2Cc_fit/s1.kkday.com/product_8298/20160521150718_VnOaq/jpg",
        "strIntroduction": "Discover the spectacular monuments of Paris at night with a commented minibus tour of the city and spectacular Lido de Paris show.",
        "strLocation": "France, Paris",
        "strOriginUrl": "https://www.kkday.com/en/product/8298",
        "strSource": "KKDAY",
        "strStyle": null,
        "strTitle": "Paris by Night: City Tour Lido Show - Pickup & Drop off Hotel"
    },
    {
        "intDurationHour": 5,
        "intOption": null,
        "intReviewStar": 0,
        "intReviewVisitor": 0,
        "intUsdCost": 2946,
        "strGuideLanguage": "Deutsch,Português,中文,日本語,English,Italiano,Français,Español",
        "strImageUrl": "http://img.kkday.com/image/get/w_1024%2Cc_fit/s1.kkday.com/product_6925/20160323073439_crFOX/jpg",
        "strIntroduction": "If you travel to Paris, don’t miss this guided tour of one of the architectural masterpieces of the French Renaissance.",
        "strLocation": "France, Paris",
        "strOriginUrl": "https://www.kkday.com/en/product/6925",
        "strSource": "KKDAY",
        "strStyle": null,
        "strTitle": "Versailles with a Guide – Skip the Line"
    },
    {
        "intDurationHour": 2,
        "intOption": null,
        "intReviewStar": 0,
        "intReviewVisitor": 0,
        "intUsdCost": 2136,
        "strGuideLanguage": "English",
        "strImageUrl": "http://img.kkday.com/image/get/w_1024%2Cc_fit/s1.kkday.com/product_7241/20160413030153_kbLLu/jpg",
        "strIntroduction": "Enjoy your evening beginning with a cruise on the Seine river, boarding Marina de Paris boat, to discover the main monuments of Paris differently.",
        "strLocation": "France, Paris",
        "strOriginUrl": "https://www.kkday.com/en/product/7241",
        "strSource": "KKDAY",
        "strStyle": null,
        "strTitle": "Early Evening Dinner Cruise \"Decouverte Menu\" - La Marina"
    },
    {
        "intDurationHour": 9,
        "intOption": null,
        "intReviewStar": 0,
        "intReviewVisitor": 0,
        "intUsdCost": 2331,
        "strGuideLanguage": "中文,日本語,English,Italiano,Français",
        "strImageUrl": "http://img.kkday.com/image/get/w_1024%2Cc_fit/s1.kkday.com/product_7213/20160414031254_0TKk5/jpg",
        "strIntroduction": "Enjoy a nice day trip from Paris to the majestic Domaine de Chantilly, extending over 19 000 acres, in one of the biggest forest of Paris outskirts.",
        "strLocation": "France, Paris",
        "strOriginUrl": "https://www.kkday.com/en/product/7213",
        "strSource": "KKDAY",
        "strStyle": null,
        "strTitle": "1 Day trip to the Château de Chantilly"
    },
    {
        "intDurationHour": 3,
        "intOption": null,
        "intReviewStar": 0,
        "intReviewVisitor": 0,
        "intUsdCost": 3302,
        "strGuideLanguage": "Deutsch,English,Español",
        "strImageUrl": "http://img.kkday.com/image/get/s1.kkday.com/product_7810/20160504032033_ITEAF/jpg",
        "strIntroduction": "The upscale neighborhood of Saint-Germain-des-Prés is a premier fashion district in Paris, and also home to upscale shops featuring hand-made sweets. Taste the trends in chocolates, pastry, and bread, offered up by exceptional gastronomic craftsmen.",
        "strLocation": "France, Paris",
        "strOriginUrl": "https://www.kkday.com/en/product/7810",
        "strSource": "KKDAY",
        "strStyle": null,
        "strTitle": "Chocolate & pastry food tour"
    },
    {
        "intDurationHour": 3,
        "intOption": null,
        "intReviewStar": 0,
        "intReviewVisitor": 0,
        "intUsdCost": 2104,
        "strGuideLanguage": "한국어,中文,日本語,English,Italiano,Français,Español",
        "strImageUrl": "http://img.kkday.com/image/get/w_1024%2Cc_fit/s1.kkday.com/product_9012/20160627083304_Y8zbk/jpg",
        "strIntroduction": "The ideal way to discover Paris for the first time. Visit Place Vendôme Square, the Orsay Museum, Place de la Concorde Square, the Opera House, the Pantheon, the Luxembourg Palace and Gardens, the Champs-Elysées, the Arc de Triomphe, and the Invalides within 3 hours. In the end, View the beautiful skyline of Paris from the 2nd floor of Eiffel Tower！",
        "strLocation": "France, Paris",
        "strOriginUrl": "https://www.kkday.com/en/product/9012",
        "strSource": "KKDAY",
        "strStyle": null,
        "strTitle": "Paris Tour and Visit to the Eiffel Tower"
    },
    {
        "intDurationHour": 3,
        "intOption": null,
        "intReviewStar": 0,
        "intReviewVisitor": 0,
        "intUsdCost": 2784,
        "strGuideLanguage": "English,Français",
        "strImageUrl": "http://img.kkday.com/image/get/w_1024%2Cc_fit/s1.kkday.com/product_7820/20160504043831_ut220/jpg",
        "strIntroduction": "Discover the very best of the Latin Quarter of Paris! Saint-Germain-des-Prés is one the most visited and appreciated areas of Paris. Learn about the history and discover various boutiques for the best experience of the area.",
        "strLocation": "France, Paris",
        "strOriginUrl": "https://www.kkday.com/en/product/7820",
        "strSource": "KKDAY",
        "strStyle": null,
        "strTitle": "Lifestyle tour in Saint-Germain-des-Prés"
    },
    {
        "intDurationHour": 5,
        "intOption": null,
        "intReviewStar": 0,
        "intReviewVisitor": 0,
        "intUsdCost": 5244,
        "strGuideLanguage": "Deutsch,русский,Português,中文,English,Italiano,Français,Español",
        "strImageUrl": "http://img.kkday.com/image/get/w_1024%2Cc_fit/s1.kkday.com/product_8392/20160525082609_eCVPk/jpg",
        "strIntroduction": "Sail across Seine river to see the illuminated sites of Paris, and at end of the cruise, get on a coach for a transfer to the Moulin Rouge. Then, enjoy the most famous show of Moulin Rouge, Féerie.",
        "strLocation": "France, Paris",
        "strOriginUrl": "https://www.kkday.com/en/product/8392",
        "strSource": "KKDAY",
        "strStyle": null,
        "strTitle": "Seine Cruise Moulin Rouge Show"
    },
    {
        "intDurationHour": 2,
        "intOption": null,
        "intReviewStar": 0,
        "intReviewVisitor": 0,
        "intUsdCost": 2528,
        "strGuideLanguage": "English",
        "strImageUrl": "http://img.kkday.com/image/get/s1.kkday.com/product_7242/20160413015555_cRZZF/jpg",
        "strIntroduction": "Enjoy a pleasant and wonderful evening on a \"La Marina de Paris\" boat. Admire the illuminations of Paris during a cruise on the Seine river for 2 hours, while you have a delicious dinner, typical french gastronomy. Magic night with the dinner cruise menu \"saveurs\".",
        "strLocation": "France, Paris",
        "strOriginUrl": "https://www.kkday.com/en/product/7242",
        "strSource": "KKDAY",
        "strStyle": null,
        "strTitle": "Dinner Cruise on the Seine \"Saveurs Menu\" - La Marina"
    },
    {
        "intDurationHour": 48,
        "intOption": null,
        "intReviewStar": 0,
        "intReviewVisitor": 0,
        "intUsdCost": 18774,
        "strGuideLanguage": "English",
        "strImageUrl": "http://img.kkday.com/image/get/w_1024%2Cc_fit/s1.kkday.com/product_8979/20160624040226_lm60p/jpg",
        "strIntroduction": "Take Euro Star and explore Paris within 2 days. Visit Arc de Triomphe, Notre Dame and Champs Elysees. Having lunch on the Eiffel Tower and cruise on the River Seine.",
        "strLocation": "France, Paris",
        "strOriginUrl": "https://www.kkday.com/en/product/8979",
        "strSource": "KKDAY",
        "strStyle": null,
        "strTitle": "Luxury Paris 2 Day Paris tour with lunch on the Eiffel Tower!"
    },
    {
        "intDurationHour": 3,
        "intOption": null,
        "intReviewStar": 0,
        "intReviewVisitor": 0,
        "intUsdCost": 3043,
        "strGuideLanguage": "English,Français",
        "strImageUrl": "http://img.kkday.com/image/get/w_1024%2Cc_fit/s1.kkday.com/product_7816/20160504040740_KGK8X/jpg",
        "strIntroduction": "Located in the north of Paris, Les Puces is known as one of the largest Flea Market in the world. For a fun-filled weekend, it’s one of the best place to go for shopping in Paris.",
        "strLocation": "France, Paris",
        "strOriginUrl": "https://www.kkday.com/en/product/7816",
        "strSource": "KKDAY",
        "strStyle": null,
        "strTitle": "Vintage Paris and the Flea market St Ouen"
    },
    {
        "intDurationHour": 1,
        "intOption": null,
        "intReviewStar": 0,
        "intReviewVisitor": 0,
        "intUsdCost": 615,
        "strGuideLanguage": "Deutsch,English,Italiano,Français",
        "strImageUrl": "http://img.kkday.com/image/get/w_1024%2Cc_fit/s1.kkday.com/product_6720/20160316010407_faIvd/jpg",
        "strIntroduction": "Get the best views of Paris from the 56th floor of the Montparnasse Tower. Enjoy the extraordinary city panoramas from the highest open-air roof terrace in the French capital.",
        "strLocation": "France, Paris",
        "strOriginUrl": "https://www.kkday.com/en/product/6720",
        "strSource": "KKDAY",
        "strStyle": null,
        "strTitle": "Montparnasse Tower"
    },
    {
        "intDurationHour": 48,
        "intOption": null,
        "intReviewStar": 0,
        "intReviewVisitor": 0,
        "intUsdCost": 15602,
        "strGuideLanguage": "English",
        "strImageUrl": "http://img.kkday.com/image/get/w_1024%2Cc_fit/s1.kkday.com/product_4058/20160229072239_tPsJi/jpeg",
        "strIntroduction": "Enjoy a fully escorted day in Paris with a river cruise, entry into the Louvre and the Eiffel Tower and an overnight in Paris",
        "strLocation": "France, Paris",
        "strOriginUrl": "https://www.kkday.com/en/product/4058",
        "strSource": "KKDAY",
        "strStyle": null,
        "strTitle": "Paris Overnight"
    },
    {
        "intDurationHour": 4,
        "intOption": null,
        "intReviewStar": 0,
        "intReviewVisitor": 0,
        "intUsdCost": 6474,
        "strGuideLanguage": "English",
        "strImageUrl": "http://img.kkday.com/image/get/w_1024%2Cc_fit/s1.kkday.com/product_8312/20160523062738_b5Zey/jpg",
        "strIntroduction": "Enjoy a romantic dinner comfortably seated on a glass covered restaurant boat of La Marina.",
        "strLocation": "France, Paris",
        "strOriginUrl": "https://www.kkday.com/en/product/8312",
        "strSource": "KKDAY",
        "strStyle": null,
        "strTitle": "Gourmet Dinner Cruise La Marina - Pickup & Drop off Hotel"
    },
    {
        "intDurationHour": 12,
        "intOption": null,
        "intReviewStar": 0,
        "intReviewVisitor": 0,
        "intUsdCost": 9452,
        "strGuideLanguage": "Deutsch,русский,Português,English,Italiano,Français,Español",
        "strImageUrl": "http://img.kkday.com/image/get/w_1024%2Cc_fit/s1.kkday.com/product_6738/20160316084530_W04YB/jpg",
        "strIntroduction": "Step back in time with this full day tour of the beautiful Loire valley and some of its most impressive chateaux. See rolling countryside, fairytale castles and stop for lunch at a charming centuries-old inn.",
        "strLocation": "France, Paris",
        "strOriginUrl": "https://www.kkday.com/en/product/6738",
        "strSource": "KKDAY",
        "strStyle": null,
        "strTitle": "Loire Castles Classical & Renaissance"
    },
    {
        "intDurationHour": 8,
        "intOption": null,
        "intReviewStar": 0,
        "intReviewVisitor": 0,
        "intUsdCost": 1683,
        "strGuideLanguage": "English,Français",
        "strImageUrl": "http://img.kkday.com/image/get/w_1024%2Cc_fit/s1.kkday.com/product_5420/20151225022601_PhwKj/jpg",
        "strIntroduction": "One small corner of Paris still holds out against the invading hordes – and your friends Asterix and Obelix are leading the resistance.",
        "strLocation": "France, Paris",
        "strOriginUrl": "https://www.kkday.com/en/product/5420",
        "strSource": "KKDAY",
        "strStyle": null,
        "strTitle": "Asterix Park"
    },
    {
        "intDurationHour": 10,
        "intOption": null,
        "intReviewStar": 0,
        "intReviewVisitor": 0,
        "intUsdCost": 14954,
        "strGuideLanguage": "中文",
        "strImageUrl": "http://img.kkday.com/image/get/w_1024%2Cc_fit/s1.kkday.com/product_9103/20160704034846_PoYq3/jpg",
        "strIntroduction": "到瓦伦索投入薰衣草花海的怀抱中，迷人的芳香与令人赞叹的美景，让你仿佛置身天堂！接着造访世外桃源的陶瓷小镇与有着天使之泪美称的圣十字湖，与大自然共舞，尽情放松！",
        "strLocation": "France, Marseille, Avignon",
        "strOriginUrl": "https://www.kkday.com/en/product/9103",
        "strSource": "KKDAY",
        "strStyle": null,
        "strTitle": "【专业包车】薰衣草海洋路线一日游"
    },
    {
        "intDurationHour": 48,
        "intOption": null,
        "intReviewStar": 0,
        "intReviewVisitor": 0,
        "intUsdCost": 16799,
        "strGuideLanguage": "Português,English,Italiano,Français,Español",
        "strImageUrl": "http://img.kkday.com/image/get/w_1024%2Cc_fit/s1.kkday.com/product_7146/20160413012605_89659/jpg",
        "strIntroduction": "Discover two popular attractions in northwest France with professional tour guides.",
        "strLocation": "France, Paris",
        "strOriginUrl": "https://www.kkday.com/en/product/7146",
        "strSource": "KKDAY",
        "strStyle": null,
        "strTitle": "2 Day Trip to Mont Saint Michel and Loire Valley Castles from Paris - Hotel Transfers"
    },
    {
        "intDurationHour": 13,
        "intOption": null,
        "intReviewStar": 0,
        "intReviewVisitor": 0,
        "intUsdCost": 4985,
        "strGuideLanguage": "English",
        "strImageUrl": "http://img.kkday.com/image/get/s1.kkday.com/product_7194/20160408093005_Lhzwm/jpg",
        "strIntroduction": "With two different theme parks, Disneyland Paris will make your dreams come true twice! Your Disneyland Paris Celebration Ticket – a 1 Day 2 Park Hopper – is superb value, allowing one day’s admission to both Disneyland Park and Walt Disney Studios Park with the freedom to hop between both Disney Parks as often as you like.",
        "strLocation": "France, Paris",
        "strOriginUrl": "https://www.kkday.com/en/product/7194",
        "strSource": "KKDAY",
        "strStyle": null,
        "strTitle": "Disneyland Paris: 1 Day 2 Parks - Pickup & Drop off Hotel"
    },
    {
        "intDurationHour": 4,
        "intOption": null,
        "intReviewStar": 0,
        "intReviewVisitor": 0,
        "intUsdCost": 5737,
        "strGuideLanguage": "Deutsch,русский,한국어,Português,中文,日本語,English,Italiano,Français,Español",
        "strImageUrl": "http://img.kkday.com/image/get/w_1024%2Cc_fit/s1.kkday.com/product_5988/20160129052101_A6vLh/jpg",
        "strIntroduction": "This night-time adventure includes a once-in-a-lifetime dinner on the first floor of the city's and a magical cruise along the Seine.",
        "strLocation": "France, Paris",
        "strOriginUrl": "https://www.kkday.com/en/product/5988",
        "strSource": "KKDAY",
        "strStyle": null,
        "strTitle": "Dinner at the Eiffel Tower with Skip-the-Line Access + Seine River Cruise"
    },
    {
        "intDurationHour": 2,
        "intOption": null,
        "intReviewStar": 4,
        "intReviewVisitor": 1,
        "intUsdCost": 2751,
        "strGuideLanguage": "English",
        "strImageUrl": "http://img.kkday.com/image/get/w_1024%2Cc_fit/s1.kkday.com/product_1204/20150527045831_5Wbmc/jpg",
        "strIntroduction": "Skip the long lines for taxis, or the hassle of navigating public transport upon arrival at Airport, and enjoy a private, chauffeur driven transfer to your city hotel in a stylish, comfortable vehicle!",
        "strLocation": "France, Paris",
        "strOriginUrl": "https://www.kkday.com/en/product/1204",
        "strSource": "KKDAY",
        "strStyle": null,
        "strTitle": "Paris Private Arrival / Departure Transfer: Charles de Gaulle Airport (CDG) Airport"
    },
    {
        "intDurationHour": 2,
        "intOption": null,
        "intReviewStar": 0,
        "intReviewVisitor": 0,
        "intUsdCost": 4661,
        "strGuideLanguage": "",
        "strImageUrl": "http://img.kkday.com/image/get/w_1024%2Cc_fit/s1.kkday.com/product_8673/20160605171353_yF1gl/jpg",
        "strIntroduction": "Experience an unforgettable Paris evening at the world-renowned Parisian cabaret, the Moulin Rouge.",
        "strLocation": "France, Paris",
        "strOriginUrl": "https://www.kkday.com/en/product/8673",
        "strSource": "KKDAY",
        "strStyle": null,
        "strTitle": "Moulin Rouge Show with Champagne - 9:00pm"
    },
    {
        "intDurationHour": 48,
        "intOption": null,
        "intReviewStar": 4,
        "intReviewVisitor": 1,
        "intUsdCost": 2614,
        "strGuideLanguage": "English",
        "strImageUrl": "http://img.kkday.com/image/get/s1.kkday.com/product_5019/20160309093845_L5Lvc/jpg",
        "strIntroduction": "Do you dare to discover every corner of London? With London Pass you have access to more than 60 tourist attractions, tours, places of interest, museums and exclusive special offers.",
        "strLocation": "United Kingdom, London",
        "strOriginUrl": "https://www.kkday.com/en/product/5019",
        "strSource": "KKDAY",
        "strStyle": null,
        "strTitle": "The London Pass with Hop-On Hop-Off Bus"
    },
    {
        "intDurationHour": 7,
        "intOption": null,
        "intReviewStar": 5,
        "intReviewVisitor": 4,
        "intUsdCost": 2965,
        "strGuideLanguage": "English",
        "strImageUrl": "http://img.kkday.com/image/get/w_1024%2Cc_fit/s1.kkday.com/product_4979/20160309092739_F15Nn/jpg",
        "strIntroduction": "Take a peek behind the scenes at the studios that created your favourite Harry Potter films. Every Muggle is guaranteed a magical time！",
        "strLocation": "United Kingdom, London",
        "strOriginUrl": "https://www.kkday.com/en/product/4979",
        "strSource": "KKDAY",
        "strStyle": null,
        "strTitle": "Warner Bros Studios : The Making of Harry Potter"
    },
    {
        "intDurationHour": 1,
        "intOption": null,
        "intReviewStar": 5,
        "intReviewVisitor": 1,
        "intUsdCost": 1165,
        "strGuideLanguage": "English",
        "strImageUrl": "http://img.kkday.com/image/get/w_1024%2Cc_fit/s1.kkday.com/product_1417/20160413041522_d24dm/jpg",
        "strIntroduction": "An iconic symbol of the London skyline, the Coca-Cola London Eye is a must-do for anybody visiting the capital city.",
        "strLocation": "United Kingdom, London",
        "strOriginUrl": "https://www.kkday.com/en/product/1417",
        "strSource": "KKDAY",
        "strStyle": null,
        "strTitle": "Coca-Cola London Eye"
    },
    {
        "intDurationHour": 12,
        "intOption": null,
        "intReviewStar": 4,
        "intReviewVisitor": 7,
        "intUsdCost": 4305,
        "strGuideLanguage": "日本語,English",
        "strImageUrl": "http://img.kkday.com/image/get/w_1024%2Cc_fit/s1.kkday.com/product_1193/20160614094018_l1Sa7/jpg",
        "strIntroduction": "Travel through the ages from prehistory to the glorious Georgian era with this fascinating full day tour taking in three of England’s sites.",
        "strLocation": "United Kingdom, London",
        "strOriginUrl": "https://www.kkday.com/en/product/1193",
        "strSource": "KKDAY",
        "strStyle": null,
        "strTitle": "Visit Windsor Castle, Stonehenge and Bath"
    },
    {
        "intDurationHour": 11,
        "intOption": null,
        "intReviewStar": 0,
        "intReviewVisitor": 0,
        "intUsdCost": 8804,
        "strGuideLanguage": "English",
        "strImageUrl": "http://img.kkday.com/image/get/s1.kkday.com/product_6078/20160617094841_0aqpU/jpg",
        "strIntroduction": "In this full-day tour of the lake, you will visit England's most scenic areas. One of the best on the lake Lakes cruise, passing many peaks.You will enjoy a deliciously British cream tea at Beatrix Potter’s family home, Lindeth Howe.",
        "strLocation": "United Kingdom, London",
        "strOriginUrl": "https://www.kkday.com/en/product/6078",
        "strSource": "KKDAY",
        "strStyle": null,
        "strTitle": "Day Trip to Lake District with Afternoon Tea"
    },
    {
        "intDurationHour": 10,
        "intOption": null,
        "intReviewStar": 0,
        "intReviewVisitor": 0,
        "intUsdCost": 4014,
        "strGuideLanguage": "English",
        "strImageUrl": "http://img.kkday.com/image/get/w_1024%2Cc_fit/s1.kkday.com/product_6821/20160324070241_dq6fw/jpg",
        "strIntroduction": "Spend a day in the rural Cotswolds region of England during this guided day tour. You’ll leave fast-paced central London and head to this relaxed and scenic part of the country. Enjoy a guided visit of Blenheim Palace and spend some time in the pretty village of Burton-on-the-Water.",
        "strLocation": "United Kingdom, London",
        "strOriginUrl": "https://www.kkday.com/en/product/6821",
        "strSource": "KKDAY",
        "strStyle": null,
        "strTitle": "Blenheim Palace and the Cotswolds with Free Lunch"
    },
    {
        "intDurationHour": 9,
        "intOption": null,
        "intReviewStar": 0,
        "intReviewVisitor": 0,
        "intUsdCost": 2881,
        "strGuideLanguage": "日本語,English",
        "strImageUrl": "http://img.kkday.com/image/get/w_1024%2Cc_fit/s1.kkday.com/product_7169/20160413014642_WfwhE/jpg",
        "strIntroduction": "Whether you’re taking a literary pilgrimage, embarking on a historical adventure or simply want to visit one of the most outstandingly beautiful areas of England, this day trip to Stratford-upon-Avon and the Cotswolds is truly unforgettable.",
        "strLocation": "United Kingdom, London",
        "strOriginUrl": "https://www.kkday.com/en/product/7169",
        "strSource": "KKDAY",
        "strStyle": null,
        "strTitle": "Shakespeare’s Stratford and the Cotswolds with Free Lunch"
    },
    {
        "intDurationHour": 5,
        "intOption": null,
        "intReviewStar": 0,
        "intReviewVisitor": 0,
        "intUsdCost": 2220,
        "strGuideLanguage": "Deutsch,русский,Português,中文,日本語,English,Italiano,Français,Español",
        "strImageUrl": "http://img.kkday.com/image/get/s1.kkday.com/product_9182/20160711072229_bNjCD/jpg",
        "strIntroduction": "What better way to see the highlight of London than from on boards a vintage double-decker bus? Enjoy great views of Westminster Abbey, Big Ben, the Houses of Parliament and the London Eye as we meander through the streets and history of our great city. The tour also includes a short trip on the river Thames and the chance to see the Changing of the Guard at Buckingham Palace!",
        "strLocation": "United Kingdom, London",
        "strOriginUrl": "https://www.kkday.com/en/product/9182",
        "strSource": "KKDAY",
        "strStyle": null,
        "strTitle": "The London Eye Classic Red Bus tour"
    },
    {
        "intDurationHour": 10,
        "intOption": null,
        "intReviewStar": 5,
        "intReviewVisitor": 2,
        "intUsdCost": 3302,
        "strGuideLanguage": "English",
        "strImageUrl": "http://img.kkday.com/image/get/w_1024%2Cc_fit/s1.kkday.com/product_1194/20160606171037_8DLVU/jpg",
        "strIntroduction": "Experience three of England’s trophy sights on this full-day trip to Windsor Castle, Stonehenge and Oxford from London. Travel by air-conditioned coach to Windsor to gaze at magnificent Windsor Castle and, if you wish, buy an entrance ticket from your guide to tour its awesome interior. Then, head for Stonehenge to marvel at this UNESCO World Heritage site, again choosing to explore independently or to buy an entrance ticket for an in-depth, audio-guided tour. Last but not least, admire the honey-stoned gems of beautiful Oxford on an included walking tour.",
        "strLocation": "United Kingdom, London",
        "strOriginUrl": "https://www.kkday.com/en/product/1194",
        "strSource": "KKDAY",
        "strStyle": null,
        "strTitle": "Windsor, Oxford and Stonehenge tour with Free Lunch"
    },
    {
        "intDurationHour": 0,
        "intOption": null,
        "intReviewStar": 0,
        "intReviewVisitor": 0,
        "intUsdCost": 1476,
        "strGuideLanguage": "English",
        "strImageUrl": "http://img.kkday.com/image/get/w_1024%2Cc_fit/s1.kkday.com/product_1197/20160617100734_0G8tq/jpg",
        "strIntroduction": "Combine one of the most quintessential English traditions with a cruise on the Thames and enjoy delicious afternoon tea in style.",
        "strLocation": "United Kingdom, London",
        "strOriginUrl": "https://www.kkday.com/en/product/1197",
        "strSource": "KKDAY",
        "strStyle": null,
        "strTitle": "London : Afternoon Tea Cruise on the River Thames"
    },
    {
        "intDurationHour": 13,
        "intOption": null,
        "intReviewStar": 0,
        "intReviewVisitor": 0,
        "intUsdCost": 4532,
        "strGuideLanguage": "English",
        "strImageUrl": "http://img.kkday.com/image/get/w_1024%2Cc_fit/s1.kkday.com/product_9236/20160713074057_AAg1g/jpg",
        "strIntroduction": "Includes entrance to Windsor Castle and Stonehenge, plus traditional lunch in a 14th century pub - why not try the fish and chips?",
        "strLocation": "United Kingdom, London",
        "strOriginUrl": "https://www.kkday.com/en/product/9236",
        "strSource": "KKDAY",
        "strStyle": null,
        "strTitle": "Windsor Castle, Stonehenge, Lacock and Bath"
    },
    {
        "intDurationHour": 10,
        "intOption": null,
        "intReviewStar": 0,
        "intReviewVisitor": 0,
        "intUsdCost": 4046,
        "strGuideLanguage": "English",
        "strImageUrl": "http://img.kkday.com/image/get/w_1024%2Cc_fit/s1.kkday.com/product_4267/20160127041219_u0IGw/jpg",
        "strIntroduction": "Enjoy a walking tour of Oxford and Cambridge, complete with the site of Harry Potter and the King's College chapel",
        "strLocation": "United Kingdom, London",
        "strOriginUrl": "https://www.kkday.com/en/product/4267",
        "strSource": "KKDAY",
        "strStyle": null,
        "strTitle": "Oxford and Cambridge with Free Lunch"
    },
    {
        "intDurationHour": 2,
        "intOption": null,
        "intReviewStar": 0,
        "intReviewVisitor": 0,
        "intUsdCost": 1877,
        "strGuideLanguage": "English",
        "strImageUrl": "http://img.kkday.com/image/get/w_1024%2Cc_fit/s1.kkday.com/product_6591/20160308032414_3oiL8/jpg",
        "strIntroduction": "With some of the most lavish sets, costumes and special effects ever created for the stage, the Phantom of the Opera is a musical phenomenon and one of the longest-running productions in the history of musicals with more than 16 years in London’s West End.",
        "strLocation": "United Kingdom, London",
        "strOriginUrl": "https://www.kkday.com/en/product/6591",
        "strSource": "KKDAY",
        "strStyle": null,
        "strTitle": "The Phantom of the Opera"
    },
    {
        "intDurationHour": 3,
        "intOption": null,
        "intReviewStar": 3,
        "intReviewVisitor": 2,
        "intUsdCost": 291,
        "strGuideLanguage": "",
        "strImageUrl": "http://img.kkday.com/image/get/w_1024%2Cc_fit/s1.kkday.com/product_4580/20160202100309_WioKY/jpg",
        "strIntroduction": "高品質上網 WiFi 機，外觀時尚，輕巧好攜帶，給你暢通無阻的上網體驗！機器直接寄送到府，取機還機超方便！",
        "strLocation": "United Kingdom, All city",
        "strOriginUrl": "https://www.kkday.com/en/product/4580",
        "strSource": "KKDAY",
        "strStyle": null,
        "strTitle": "Europe Pocket WiFi"
    },
    {
        "intDurationHour": 5,
        "intOption": null,
        "intReviewStar": 0,
        "intReviewVisitor": 0,
        "intUsdCost": 2104,
        "strGuideLanguage": "English",
        "strImageUrl": "http://img.kkday.com/image/get/s1.kkday.com/product_9249/20160714070326_Ksve8/jpg",
        "strIntroduction": "Enjoy great views of Westminster Abbey, Big Ben, the Houses of Parliament and the London Eye as we meander through the streets and history of our great city. The tour also includes a cruise on the river Thames and the chance to see the Changing of the Guard at Buckingham Palace.",
        "strLocation": "United Kingdom, London",
        "strOriginUrl": "https://www.kkday.com/en/product/9249",
        "strSource": "KKDAY",
        "strStyle": null,
        "strTitle": "Open Top Bus tour with Fish & Chips Pub Lunch"
    },
    {
        "intDurationHour": 2,
        "intOption": null,
        "intReviewStar": 0,
        "intReviewVisitor": 0,
        "intUsdCost": 421,
        "strGuideLanguage": "English",
        "strImageUrl": "http://img.kkday.com/image/get/w_1024%2Cc_fit/s1.kkday.com/product_1176/20150525084328_oIZLa/jpg",
        "strIntroduction": "Everyone had a theory as to who the ripper was… there were rumours it was a butcher, a doctor or even a royal…",
        "strLocation": "United Kingdom, London",
        "strOriginUrl": "https://www.kkday.com/en/product/1176",
        "strSource": "KKDAY",
        "strStyle": null,
        "strTitle": "Jack the Ripper walking tour"
    },
    {
        "intDurationHour": 3,
        "intOption": null,
        "intReviewStar": 0,
        "intReviewVisitor": 0,
        "intUsdCost": 2823,
        "strGuideLanguage": "English",
        "strImageUrl": "http://img.kkday.com/image/get/w_1024%2Cc_fit/s1.kkday.com/product_6067/20160208072444_l4z8v/jpg",
        "strIntroduction": "The Serengeti comes to life as never before through the extraordinary vision that is The Lion King. Come and enter a unique three hour-long adventure where you will be transported into the heart of Africa.",
        "strLocation": "United Kingdom, London",
        "strOriginUrl": "https://www.kkday.com/en/product/6067",
        "strSource": "KKDAY",
        "strStyle": null,
        "strTitle": "The Lion King Musical Tickets"
    },
    {
        "intDurationHour": 0,
        "intOption": null,
        "intReviewStar": 4,
        "intReviewVisitor": 2,
        "intUsdCost": 4337,
        "strGuideLanguage": "English",
        "strImageUrl": "http://img.kkday.com/image/get/w_1024%2Cc_fit/s1.kkday.com/product_1203/20160413045301_EQmJa/jpg",
        "strIntroduction": "See the best that royal London has to offer in a single morning!",
        "strLocation": "United Kingdom, London",
        "strOriginUrl": "https://www.kkday.com/en/product/1203",
        "strSource": "KKDAY",
        "strStyle": null,
        "strTitle": "Royal London tour"
    },
    {
        "intDurationHour": 3,
        "intOption": null,
        "intReviewStar": 4,
        "intReviewVisitor": 3,
        "intUsdCost": 1068,
        "strGuideLanguage": "English",
        "strImageUrl": "http://img.kkday.com/image/get/w_1024%2Cc_fit/s1.kkday.com/product_1350/20150525093008_Z8N2Y/jpg",
        "strIntroduction": "An alternative bike tour for those longing to see a different side to London.",
        "strLocation": "United Kingdom, London",
        "strOriginUrl": "https://www.kkday.com/en/product/1350",
        "strSource": "KKDAY",
        "strStyle": null,
        "strTitle": "Secret London Bike Tour"
    },
    {
        "intDurationHour": 0,
        "intOption": null,
        "intReviewStar": 5,
        "intReviewVisitor": 2,
        "intUsdCost": 1651,
        "strGuideLanguage": "English",
        "strImageUrl": "http://img.kkday.com/image/get/w_1024%2Cc_fit/s1.kkday.com/product_1181/20160126072220_1P986/jpg",
        "strIntroduction": "This is the original and best London rock tour! A fully-guided mini-coach journey, such as Jimi Hendrix's flat & the Beatles Abbey Road.",
        "strLocation": "United Kingdom, London",
        "strOriginUrl": "https://www.kkday.com/en/product/1181",
        "strSource": "KKDAY",
        "strStyle": null,
        "strTitle": "London Rock 'n' Roll History Tour"
    },
    {
        "intDurationHour": 2,
        "intOption": null,
        "intReviewStar": 5,
        "intReviewVisitor": 3,
        "intUsdCost": 453,
        "strGuideLanguage": "English",
        "strImageUrl": "http://img.kkday.com/image/get/w_1024%2Cc_fit/s1.kkday.com/product_1301/20160125034318_2WmKw/jpg",
        "strIntroduction": "See the supernatural side of Edinburgh on a 75-minute walking tour. Pay attention as your ghostly guide, Adam Lyal, leads you through the picturesque cobbled streets of the old city, delighting you with tales of ghosts, witchcraft, and body snatching.",
        "strLocation": "United Kingdom, Edinburgh",
        "strOriginUrl": "https://www.kkday.com/en/product/1301",
        "strSource": "KKDAY",
        "strStyle": null,
        "strTitle": "Murder and Mystery Walking Tour of Edinburgh"
    },
    {
        "intDurationHour": 12,
        "intOption": null,
        "intReviewStar": 0,
        "intReviewVisitor": 0,
        "intUsdCost": 2298,
        "strGuideLanguage": "English",
        "strImageUrl": "http://img.kkday.com/image/get/w_1024%2Cc_fit/s1.kkday.com/product_1298/20160413065042_XwPUp/jpg",
        "strIntroduction": "Tour the most picturesque regions of Scotland on a full-day tour from Edinburgh. Visit Loch Ness, Glencoe, and Rannoch Moor, and discover the area's amazing history. The tour includes an optional boat ride on Loch Ness, looking for the legendary monster.",
        "strLocation": "United Kingdom, Edinburgh",
        "strOriginUrl": "https://www.kkday.com/en/product/1298",
        "strSource": "KKDAY",
        "strStyle": null,
        "strTitle": "Loch Ness, Glencoe and Highlands Small Group Tour"
    },
    {
        "intDurationHour": 1,
        "intOption": null,
        "intReviewStar": 4,
        "intReviewVisitor": 3,
        "intUsdCost": 971,
        "strGuideLanguage": "English",
        "strImageUrl": "http://img.kkday.com/image/get/w_1024%2Cc_fit/s1.kkday.com/product_1199/20160206135411_3At6u/jpg",
        "strIntroduction": "Be thrilled as you pass through the vibrant city of London lit up against the night sky. Climb aboard this open top bus and enjoy a fun and informative guided tour. See Big Ben, Harrods, the London Eye and Trafalgar Square.",
        "strLocation": "United Kingdom, London",
        "strOriginUrl": "https://www.kkday.com/en/product/1199",
        "strSource": "KKDAY",
        "strStyle": null,
        "strTitle": "London Night Sightseeing Tour"
    },
    {
        "intDurationHour": 2,
        "intOption": null,
        "intReviewStar": 0,
        "intReviewVisitor": 0,
        "intUsdCost": 486,
        "strGuideLanguage": "English",
        "strImageUrl": "http://img.kkday.com/image/get/w_1024%2Cc_fit/s1.kkday.com/product_2457/20151222050953_tziQH/jpg",
        "strIntroduction": "Karl Marx was the most influential thinker of modern times. Join us as we walk you through the life, times and ideas of Karl Marx!",
        "strLocation": "United Kingdom, London",
        "strOriginUrl": "https://www.kkday.com/en/product/2457",
        "strSource": "KKDAY",
        "strStyle": null,
        "strTitle": "Karl Marx The Walking Tour"
    },
    {
        "intDurationHour": 7,
        "intOption": null,
        "intReviewStar": 4,
        "intReviewVisitor": 1,
        "intUsdCost": 1974,
        "strGuideLanguage": "English",
        "strImageUrl": "http://img.kkday.com/image/get/w_1024%2Cc_fit/s1.kkday.com/product_1336/20160413063002_fkljv/jpg",
        "strIntroduction": "Enjoy a scenic tour of one of England’s most picturesque regions on a full-day tour of the Lake District. Visit mysterious Castlerigg Stone Circle, and see Lakeland villages. Cruise on one of the Lake District’s best bodies of water past mountain peaks.",
        "strLocation": "United Kingdom, Lake District",
        "strOriginUrl": "https://www.kkday.com/en/product/1336",
        "strSource": "KKDAY",
        "strStyle": null,
        "strTitle": "Full-Day Ten Lakes Spectacular Lake District Tour"
    },
    {
        "intDurationHour": 2,
        "intOption": null,
        "intReviewStar": 0,
        "intReviewVisitor": 0,
        "intUsdCost": 787,
        "strGuideLanguage": "Deutsch,日本語,English,Italiano,Français,Español",
        "strImageUrl": "http://img.kkday.com/image/get/w_1024%2Cc_fit/s1.kkday.com/product_5750/20160413063955_O6xlO/jpg",
        "strIntroduction": "Come discover Queen Victoria’s story in some of the most elegant surroundings in London.",
        "strLocation": "United Kingdom, London",
        "strOriginUrl": "https://www.kkday.com/en/product/5750",
        "strSource": "KKDAY",
        "strStyle": null,
        "strTitle": "Kensington Palace"
    },
    {
        "intDurationHour": 8,
        "intOption": null,
        "intReviewStar": 0,
        "intReviewVisitor": 0,
        "intUsdCost": 1780,
        "strGuideLanguage": "English",
        "strImageUrl": "http://img.kkday.com/image/get/w_1024%2Cc_fit/s1.kkday.com/product_4213/20160413045631_3scNj/jpg",
        "strIntroduction": "Castle & Lochs of the Western Highlands “The ideal tour to enjoy beautiful scenery and see some of Scotland’s most famous Castles\"",
        "strLocation": "United Kingdom, Edinburgh",
        "strOriginUrl": "https://www.kkday.com/en/product/4213",
        "strSource": "KKDAY",
        "strStyle": null,
        "strTitle": "Doune Castle, Loch Lomond & The Western Highlands"
    },
    {
        "intDurationHour": 4,
        "intOption": null,
        "intReviewStar": 5,
        "intReviewVisitor": 2,
        "intUsdCost": 906,
        "strGuideLanguage": "English",
        "strImageUrl": "http://img.kkday.com/image/get/w_1024%2Cc_fit/s1.kkday.com/product_1421/20160328043227_PNrRS/jpg",
        "strIntroduction": "Says cheers to London and explore some of the city’s most historic pubs, taverns and alehouses. Drink the city’s finest brews !",
        "strLocation": "United Kingdom, London",
        "strOriginUrl": "https://www.kkday.com/en/product/1421",
        "strSource": "KKDAY",
        "strStyle": null,
        "strTitle": "Drink London! Historical Pub Walking Tour"
    },
    {
        "intDurationHour": 9,
        "intOption": null,
        "intReviewStar": 0,
        "intReviewVisitor": 0,
        "intUsdCost": 1683,
        "strGuideLanguage": "English",
        "strImageUrl": "http://img.kkday.com/image/get/w_1024%2Cc_fit/s1.kkday.com/product_4057/20160208160601_bD5iI/jpg",
        "strIntroduction": "Experience the Scottish cultural icon that is most appreciated around the world -- whisky!",
        "strLocation": "United Kingdom, Edinburgh",
        "strOriginUrl": "https://www.kkday.com/en/product/4057",
        "strSource": "KKDAY",
        "strStyle": null,
        "strTitle": "Highland Whisky Experience"
    },
    {
        "intDurationHour": 0,
        "intOption": null,
        "intReviewStar": 0,
        "intReviewVisitor": 0,
        "intUsdCost": 531,
        "strGuideLanguage": "English",
        "strImageUrl": "http://img.kkday.com/image/get/w_1024%2Cc_fit/s1.kkday.com/product_1341/20160207022949_0Yah5/jpg",
        "strIntroduction": "Hop-on and hop-off City Sightseeing double-deckers and explore Liverpool Top Attractions. Labeled as the World Capital of Pop, Liverpool is especially famous for being the home town of the Beatles. It is also renowned for its port and maritime activities, its football teams, its monuments and architecture as well as its unique atmosphere vibrant with cafés, hip hotels and trendy bars.",
        "strLocation": "United Kingdom, Liverpool",
        "strOriginUrl": "https://www.kkday.com/en/product/1341",
        "strSource": "KKDAY",
        "strStyle": null,
        "strTitle": "Liverpool City Hop-on Hop-off Tour"
    },
    {
        "intDurationHour": 16,
        "intOption": null,
        "intReviewStar": 0,
        "intReviewVisitor": 0,
        "intUsdCost": 5891,
        "strGuideLanguage": "English",
        "strImageUrl": "http://img.kkday.com/image/get/w_1024%2Cc_fit/s1.kkday.com/product_1346/20150525092653_r7nUp/jpg",
        "strIntroduction": "Swing back to the Sixties with this day trip from London to Liverpool, the home town of the Fab Four and the epicentre of Beatlemania.",
        "strLocation": "United Kingdom, London",
        "strOriginUrl": "https://www.kkday.com/en/product/1346",
        "strSource": "KKDAY",
        "strStyle": null,
        "strTitle": "The magical Beatles tour of Liverpool"
    },
    {
        "intDurationHour": 0,
        "intOption": null,
        "intReviewStar": 0,
        "intReviewVisitor": 0,
        "intUsdCost": 5503,
        "strGuideLanguage": "English",
        "strImageUrl": "http://img.kkday.com/image/get/w_1024%2Cc_fit/s1.kkday.com/product_1444/20160422100730_KMfdJ/jpg",
        "strIntroduction": "Book your airport transfer from London Heathrow Airport and Gatwick Airport to your centrally located London hotel!",
        "strLocation": "United Kingdom, London",
        "strOriginUrl": "https://www.kkday.com/en/product/1444",
        "strSource": "KKDAY",
        "strStyle": null,
        "strTitle": "London Airport Private Arrival Transfer"
    },
    {
        "intDurationHour": 2,
        "intOption": null,
        "intReviewStar": 0,
        "intReviewVisitor": 0,
        "intUsdCost": 1016,
        "strGuideLanguage": "Deutsch,русский,Português,中文,日本語,English,Italiano,Français,Español",
        "strImageUrl": "http://img.kkday.com/image/get/s1.kkday.com/product_8795/20160614082133_DC8bE/jpg",
        "strIntroduction": "The iconic and beautiful royal residence of Buckingham Palace serves as both the office and London home of Her Majesty The Queen, as well as the administrative headquarters of the Royal Household. It is one of the only working royal palaces remaining in the world today and an absolute must-see on any trip to London.",
        "strLocation": "United Kingdom, London",
        "strOriginUrl": "https://www.kkday.com/en/product/8795",
        "strSource": "KKDAY",
        "strStyle": null,
        "strTitle": "Buckingham Palace Tickets"
    },
    {
        "intDurationHour": 10,
        "intOption": null,
        "intReviewStar": 0,
        "intReviewVisitor": 0,
        "intUsdCost": 3561,
        "strGuideLanguage": "English",
        "strImageUrl": "http://img.kkday.com/image/get/w_1024%2Cc_fit/s1.kkday.com/product_8892/20160618102442_XCocP/jpg",
        "strIntroduction": "Visit Burford, Bibury and Northern Cotswolds. Marvel at the view of the most beautiful village in England and have a unforgettable lunch.",
        "strLocation": "United Kingdom, London",
        "strOriginUrl": "https://www.kkday.com/en/product/8892",
        "strSource": "KKDAY",
        "strStyle": null,
        "strTitle": "Lunch in the Cotswolds with lunch in the prettiest village in Britain"
    },
    {
        "intDurationHour": 10,
        "intOption": null,
        "intReviewStar": 0,
        "intReviewVisitor": 0,
        "intUsdCost": 3431,
        "strGuideLanguage": "English",
        "strImageUrl": "http://img.kkday.com/image/get/w_1024%2Cc_fit/s1.kkday.com/product_7160/20160407095458_KEx2j/jpg",
        "strIntroduction": "Enjoy a full day discovering the treasures of Kent, including visits to romantic Leeds Castle, historic Canterbury Cathedral, the dramatic White Cliffs of Dover, and the legendary Greenwich Meridian.",
        "strLocation": "United Kingdom, London",
        "strOriginUrl": "https://www.kkday.com/en/product/7160",
        "strSource": "KKDAY",
        "strStyle": null,
        "strTitle": "Leeds Castle, Canterbury, Dover & Greenwich River Boat Ride with Free SUBWAY Lunch"
    },
    {
        "intDurationHour": 3,
        "intOption": null,
        "intReviewStar": 3,
        "intReviewVisitor": 2,
        "intUsdCost": 647,
        "strGuideLanguage": "Deutsch,한국어,中文,日本語,English,Italiano,Français,Español",
        "strImageUrl": "http://img.kkday.com/image/get/w_1024%2Cc_fit/s1.kkday.com/product_6815/20160319010300_m9JEA/jpg",
        "strIntroduction": "Skip the line and enjoy discounted fast-track entrance to the London landmark of St Paul's Cathedral. Explore the cathedral floor and crypt, climb its 3 galleries and view panoramic London from the top of the dome. Multimedia guides and tours provided.",
        "strLocation": "United Kingdom, London",
        "strOriginUrl": "https://www.kkday.com/en/product/6815",
        "strSource": "KKDAY",
        "strStyle": null,
        "strTitle": "St Paul's Cathedral Tickets - Skip the Line"
    },
    {
        "intDurationHour": 0,
        "intOption": null,
        "intReviewStar": 0,
        "intReviewVisitor": 0,
        "intUsdCost": 2331,
        "strGuideLanguage": "English",
        "strImageUrl": "http://img.kkday.com/image/get/w_1024%2Cc_fit/s1.kkday.com/product_6082/20160214113232_kV6KZ/jpg",
        "strIntroduction": "Experience an entertaining medieval banquet in the heart of London! Join King Henry VIII and his royal guests as you tuck into a delicious 4-course medieval feast while being entertained by a number of specialty acts. Enjoy ale and wine with dinner.",
        "strLocation": "United Kingdom, Liverpool, London",
        "strOriginUrl": "https://www.kkday.com/en/product/6082",
        "strSource": "KKDAY",
        "strStyle": null,
        "strTitle": "London: 4-Hour Medieval Banquet at Ivory House"
    },
    {
        "intDurationHour": 4,
        "intOption": null,
        "intReviewStar": 0,
        "intReviewVisitor": 0,
        "intUsdCost": 2518,
        "strGuideLanguage": "English",
        "strImageUrl": "http://img.kkday.com/image/get/w_1024%2Cc_fit/s1.kkday.com/product_5719/20160204084232_04txC/jpg",
        "strIntroduction": "Step inside magnificent Buckingham Palace and explore the rooms used by the Royals before enjoying traditional afternoon tea with this first-class",
        "strLocation": "United Kingdom, London",
        "strOriginUrl": "https://www.kkday.com/en/product/5719",
        "strSource": "KKDAY",
        "strStyle": null,
        "strTitle": "Buckingham Palace and afternoon tea"
    },
    {
        "intDurationHour": 3,
        "intOption": null,
        "intReviewStar": 0,
        "intReviewVisitor": 0,
        "intUsdCost": 1789,
        "strGuideLanguage": "English",
        "strImageUrl": "http://img.kkday.com/image/get/w_1024%2Cc_fit/s1.kkday.com/product_6958/20160324154430_CuK30/jpg",
        "strIntroduction": "Pay homage to the King of Pop in the most spectacular way possible at Thriller – Live, the highest-octane show in town.",
        "strLocation": "United Kingdom, London",
        "strOriginUrl": "https://www.kkday.com/en/product/6958",
        "strSource": "KKDAY",
        "strStyle": null,
        "strTitle": "Thriller - Live show"
    }
]