[
    {
        "intDurationHour": 2,
        "intOption": null,
        "intReviewStar": 0,
        "intReviewVisitor": 0,
        "intUsdCost": 15,
        "strGuideLanguage": "English",
        "strImageUrl": "http://img.kkday.com/image/get/w_1024%2Cc_fit/s1.kkday.com/product_2457/20151222050953_tziQH/jpg",
        "strIntroduction": "Karl Marx was the most influential thinker of modern times. Join us as we walk you through the life, times and ideas of Karl Marx!",
        "strLocation": "United Kingdom, London",
        "strOriginUrl": "https://www.kkday.com/en/product/2457",
        "strSource": "KKDAY",
        "strStyle": null,
        "strTitle": "Karl Marx The Walking Tour"
    },
    {
        "intDurationHour": 720,
        "intOption": null,
        "intReviewStar": 4,
        "intReviewVisitor": 2,
        "intUsdCost": 50,
        "strGuideLanguage": "",
        "strImageUrl": "http://img.kkday.com/image/get/w_1024%2Cc_fit/s1.kkday.com/product_6051/20160205073647_y28yP/jpg",
        "strIntroduction": "One prepaid SIM to be used in 11 European countries, with ultra-high 12GB data and 300 minutes of intra-network airtime!",
        "strLocation": "United Kingdom, All city",
        "strOriginUrl": "https://www.kkday.com/en/product/6051",
        "strSource": "KKDAY",
        "strStyle": null,
        "strTitle": "European SIM Card: 12GB Data＋300 Mins Airtime (intra-network)"
    },
    {
        "intDurationHour": 12,
        "intOption": null,
        "intReviewStar": 0,
        "intReviewVisitor": 0,
        "intUsdCost": 77,
        "strGuideLanguage": "English",
        "strImageUrl": "http://img.kkday.com/image/get/w_1024%2Cc_fit/s1.kkday.com/product_6818/20160319142559_eRIpP/jpg",
        "strIntroduction": "Departing central London you travel west until you meet the River Thames at Runnymeade where in 1215 King John sealed the Magna Carta and founded the modern rule of law. From here it is a short drive through Windsor Great Park to the Royal town of Windsor, home to one of the Queen’s most impressive residences. During your stop here you will have time to visit the Castle and State Apartments.",
        "strLocation": "United Kingdom, London",
        "strOriginUrl": "https://www.kkday.com/en/product/6818",
        "strSource": "KKDAY",
        "strStyle": null,
        "strTitle": "Traditional England - Royal Windsor, real ales, cream teas and riverside walks"
    },
    {
        "intDurationHour": 11,
        "intOption": null,
        "intReviewStar": 0,
        "intReviewVisitor": 0,
        "intUsdCost": 120,
        "strGuideLanguage": "English",
        "strImageUrl": "http://img.kkday.com/image/get/w_1024%2Cc_fit/s1.kkday.com/product_8891/20160728033834_aUsd4/jpg",
        "strIntroduction": "Spend one day visit Warwick Castle, Stratford, Oxford and the Cotswolds. Marvel at the charming idyllic sceneries and stunning medieval architectures.",
        "strLocation": "United Kingdom, London",
        "strOriginUrl": "https://www.kkday.com/en/product/8891",
        "strSource": "KKDAY",
        "strStyle": null,
        "strTitle": "Warwick Castle, Stratford, Oxford & the Cotswolds"
    },
    {
        "intDurationHour": 5,
        "intOption": null,
        "intReviewStar": 4,
        "intReviewVisitor": 1,
        "intUsdCost": 54,
        "strGuideLanguage": "Deutsch,Português,日本語,English,Italiano,Français,Español",
        "strImageUrl": "http://img.kkday.com/image/get/s1.kkday.com/product_7164/20160406091709_otGZY/jpg",
        "strIntroduction": "Explore the mysteries of the legendary stone circle of Stonehenge on a 5-hour tour from London. Learn about some of the theories surrounding the 5,000-year-old monument, and enjoy dramatic views of Salisbury Plain and the West of England.",
        "strLocation": "United Kingdom, London",
        "strOriginUrl": "https://www.kkday.com/en/product/7164",
        "strSource": "KKDAY",
        "strStyle": null,
        "strTitle": "Simply Stonehenge Tour - Morning"
    },
    {
        "intDurationHour": 720,
        "intOption": null,
        "intReviewStar": 0,
        "intReviewVisitor": 0,
        "intUsdCost": 95,
        "strGuideLanguage": "English",
        "strImageUrl": "http://img.kkday.com/image/get/w_1024%2Cc_fit/s1.kkday.com/product_6760/20160318030203_3LwfD/jpg",
        "strIntroduction": "iVenture card London is the ultimate attractions, dining and entertainment card! Offering up to 40% savings to top attractions, sightseeing tours, theater shows and restaurants. You choose what you want to see, when you want to see it !",
        "strLocation": "United Kingdom, London",
        "strOriginUrl": "https://www.kkday.com/en/product/6760",
        "strSource": "KKDAY",
        "strStyle": null,
        "strTitle": "iVenture Card London"
    },
    {
        "intDurationHour": 1,
        "intOption": null,
        "intReviewStar": 3,
        "intReviewVisitor": 1,
        "intUsdCost": 28,
        "strGuideLanguage": "English",
        "strImageUrl": "http://img.kkday.com/image/get/w_1024%2Cc_fit/s1.kkday.com/product_4970/20151209024150_suibm/jpg",
        "strIntroduction": "On-board actors and technical trickery combine to create the most entertaining tour in town!",
        "strLocation": "United Kingdom, London",
        "strOriginUrl": "https://www.kkday.com/en/product/4970",
        "strSource": "KKDAY",
        "strStyle": null,
        "strTitle": "Ghost bus tour"
    },
    {
        "intDurationHour": 0,
        "intOption": null,
        "intReviewStar": 0,
        "intReviewVisitor": 0,
        "intUsdCost": 37,
        "strGuideLanguage": "English",
        "strImageUrl": "http://img.kkday.com/image/get/w_1024%2Cc_fit/s1.kkday.com/product_6074/20160209065757_1yoab/jpg",
        "strIntroduction": "Brace yourself for a heart-stopping experience at The London Dungeon as the untold terrors of London’s past are brought to life before you. This simulated horror from history recalls atrocities from the past, and is sure to set your heart rate soaring!",
        "strLocation": "United Kingdom, London",
        "strOriginUrl": "https://www.kkday.com/en/product/6074",
        "strSource": "KKDAY",
        "strStyle": null,
        "strTitle": "The London Dungeon Experience - Priority Entry"
    },
    {
        "intDurationHour": 12,
        "intOption": null,
        "intReviewStar": 0,
        "intReviewVisitor": 0,
        "intUsdCost": 61,
        "strGuideLanguage": "English",
        "strImageUrl": "http://img.kkday.com/image/get/w_1024%2Cc_fit/s1.kkday.com/product_5648/20151230023858_uksWD/jpeg",
        "strIntroduction": "A day spent in the Borderlands of Scotland and England. Harry Potter movie series",
        "strLocation": "United Kingdom, Edinburgh",
        "strOriginUrl": "https://www.kkday.com/en/product/5648",
        "strSource": "KKDAY",
        "strStyle": null,
        "strTitle": "Alnwick Castle, Northumberland Coast and the Borders (1 day tour)"
    },
    {
        "intDurationHour": 0,
        "intOption": null,
        "intReviewStar": 0,
        "intReviewVisitor": 0,
        "intUsdCost": 72,
        "strGuideLanguage": "English",
        "strImageUrl": "http://img.kkday.com/image/get/w_1024%2Cc_fit/s1.kkday.com/product_6082/20160214113232_kV6KZ/jpg",
        "strIntroduction": "Experience an entertaining medieval banquet in the heart of London! Join King Henry VIII and his royal guests as you tuck into a delicious 4-course medieval feast while being entertained by a number of specialty acts. Enjoy ale and wine with dinner.",
        "strLocation": "United Kingdom, Liverpool, London",
        "strOriginUrl": "https://www.kkday.com/en/product/6082",
        "strSource": "KKDAY",
        "strStyle": null,
        "strTitle": "London: 4-Hour Medieval Banquet at Ivory House"
    },
    {
        "intDurationHour": 2,
        "intOption": null,
        "intReviewStar": 0,
        "intReviewVisitor": 0,
        "intUsdCost": 21,
        "strGuideLanguage": "English",
        "strImageUrl": "http://img.kkday.com/image/get/s1.kkday.com/product_7175/20160408061651_wU9Ta/jpg",
        "strIntroduction": "Relive Wembley Stadium’s greatest moments in sport and culture on a 75-minute fully guided tour. Get behind-the-scenes access to the Players Tunnel, England Dressing Room, and Royal Box, and enjoy spectacular views of the entire stadium.",
        "strLocation": "United Kingdom, London",
        "strOriginUrl": "https://www.kkday.com/en/product/7175",
        "strSource": "KKDAY",
        "strStyle": null,
        "strTitle": "Wembley Stadium Tour"
    },
    {
        "intDurationHour": 8,
        "intOption": null,
        "intReviewStar": 0,
        "intReviewVisitor": 0,
        "intUsdCost": 37,
        "strGuideLanguage": "English",
        "strImageUrl": "http://img.kkday.com/image/get/w_1024%2Cc_fit/s1.kkday.com/product_5036/20151210044302_ADYxr/jpg",
        "strIntroduction": "Put the therapy into retail with a day devoted solely to shopping at the ever better Bicester Village in Oxfordshire, a little over an hour away from London.",
        "strLocation": "United Kingdom, London",
        "strOriginUrl": "https://www.kkday.com/en/product/5036",
        "strSource": "KKDAY",
        "strStyle": null,
        "strTitle": "Shopping Express : Bicester Village"
    },
    {
        "intDurationHour": 3,
        "intOption": null,
        "intReviewStar": 0,
        "intReviewVisitor": 0,
        "intUsdCost": 109,
        "strGuideLanguage": "English",
        "strImageUrl": "http://img.kkday.com/image/get/w_1024%2Cc_fit/s1.kkday.com/product_6966/20160325041212_1WdeW/jpg",
        "strIntroduction": "Come for the best night out on the River ThaEnjoy a wonderful 3-and-a-quarter-hour dinner cruise on the River Thames as you feast on a 4-course meal. Enjoy a live cabaret performance and dance into the night as you cruise past London's illuminated monuments as far as the Thames Barrier and back. mes with an evening that promises good food, entertainment and fabulous views.",
        "strLocation": "United Kingdom, London",
        "strOriginUrl": "https://www.kkday.com/en/product/6966",
        "strSource": "KKDAY",
        "strStyle": null,
        "strTitle": "London Showboat dinner cruise"
    },
    {
        "intDurationHour": 10,
        "intOption": null,
        "intReviewStar": 0,
        "intReviewVisitor": 0,
        "intUsdCost": 101,
        "strGuideLanguage": "English",
        "strImageUrl": "http://img.kkday.com/image/get/w_1024%2Cc_fit/s1.kkday.com/product_7079/20160615042208_OTlUP/jpg",
        "strIntroduction": "Explore the beauty of wider England and visit two incredible UK attractions – Stonehenge and the city of Bath! A day of ancient history, breathtaking scenery and beautiful architecture, this fully guided tour is the best way to see some of the most impressive parts of England.",
        "strLocation": "United Kingdom, London",
        "strOriginUrl": "https://www.kkday.com/en/product/7079",
        "strSource": "KKDAY",
        "strStyle": null,
        "strTitle": "Stonehenge and Bath Tour with Free SUBWAY Lunch"
    },
    {
        "intDurationHour": 10,
        "intOption": null,
        "intReviewStar": 0,
        "intReviewVisitor": 0,
        "intUsdCost": 68,
        "strGuideLanguage": "English",
        "strImageUrl": "http://img.kkday.com/image/get/w_1024%2Cc_fit/s1.kkday.com/product_7162/20160615035527_cUqYd/jpg",
        "strIntroduction": "Discover the beauty of the English countryside on a day tour of the Cotswolds, and Stratford-upon-Avon from London. Visit the birthplace of William Shakespeare, the top sites of one of the world’s oldest university towns, and much more.",
        "strLocation": "United Kingdom, London",
        "strOriginUrl": "https://www.kkday.com/en/product/7162",
        "strSource": "KKDAY",
        "strStyle": null,
        "strTitle": "Stratford-upon-Avon and the Cotswolds without Entrances"
    },
    {
        "intDurationHour": 8,
        "intOption": null,
        "intReviewStar": 0,
        "intReviewVisitor": 0,
        "intUsdCost": 113,
        "strGuideLanguage": "English",
        "strImageUrl": "http://img.kkday.com/image/get/w_1024%2Cc_fit/s1.kkday.com/product_6891/20160321134044_6cd9D/jpg",
        "strIntroduction": "Spend your day experiencing some of London's greatest sites and traditions.",
        "strLocation": "United Kingdom, London",
        "strOriginUrl": "https://www.kkday.com/en/product/6891",
        "strSource": "KKDAY",
        "strStyle": null,
        "strTitle": "Combo Saver - Westmister Abbey & National Gallery"
    },
    {
        "intDurationHour": 3,
        "intOption": null,
        "intReviewStar": 0,
        "intReviewVisitor": 0,
        "intUsdCost": 31,
        "strGuideLanguage": "Español",
        "strImageUrl": "http://img.kkday.com/image/get/w_1024%2Cc_fit/s1.kkday.com/product_7020/20160327101240_reu7I/jpg",
        "strIntroduction": "Visit both the old town and new town of Edinburgh in 3 hours with our panoramic tour",
        "strLocation": "United Kingdom, Edinburgh",
        "strOriginUrl": "https://www.kkday.com/en/product/7020",
        "strSource": "KKDAY",
        "strStyle": null,
        "strTitle": "Panoramic Tour of Edinburgh"
    },
    {
        "intDurationHour": 3,
        "intOption": null,
        "intReviewStar": 0,
        "intReviewVisitor": 0,
        "intUsdCost": 60,
        "strGuideLanguage": "English",
        "strImageUrl": "http://img.kkday.com/image/get/w_1024%2Cc_fit/s1.kkday.com/product_6697/20160315060134_dmMdt/jpg",
        "strIntroduction": "Based on Victor Hugo’s classic novel, Les Miserables is an epic and uplifting story about the survival of the human spirit.",
        "strLocation": "United Kingdom, London",
        "strOriginUrl": "https://www.kkday.com/en/product/6697",
        "strSource": "KKDAY",
        "strStyle": null,
        "strTitle": "Les Miserables - Queen's Theatre"
    },
    {
        "intDurationHour": 2,
        "intOption": null,
        "intReviewStar": 0,
        "intReviewVisitor": 0,
        "intUsdCost": 31,
        "strGuideLanguage": "Deutsch,русский,Português,中文,日本語,English,Italiano,Français,Español",
        "strImageUrl": "http://img.kkday.com/image/get/s1.kkday.com/product_8795/20160614082133_DC8bE/jpg",
        "strIntroduction": "The iconic and beautiful royal residence of Buckingham Palace serves as both the office and London home of Her Majesty The Queen, as well as the administrative headquarters of the Royal Household. It is one of the only working royal palaces remaining in the world today and an absolute must-see on any trip to London.",
        "strLocation": "United Kingdom, London",
        "strOriginUrl": "https://www.kkday.com/en/product/8795",
        "strSource": "KKDAY",
        "strStyle": null,
        "strTitle": "Buckingham Palace Tickets"
    },
    {
        "intDurationHour": 0,
        "intOption": null,
        "intReviewStar": 0,
        "intReviewVisitor": 0,
        "intUsdCost": 34,
        "strGuideLanguage": "English",
        "strImageUrl": "http://img.kkday.com/image/get/w_1024%2Cc_fit/s1.kkday.com/product_6072/20160209060721_e9iq4/jpg",
        "strIntroduction": "Take to the streets of London on the quirky yellow Duck truck and see the capital's most famous sites, including Houses of Parliament and Downing Street. The Duck then transforms into a boat, taking you off on a 30-minute adventure down the River Thames!",
        "strLocation": "United Kingdom, London",
        "strOriginUrl": "https://www.kkday.com/en/product/6072",
        "strSource": "KKDAY",
        "strStyle": null,
        "strTitle": "London Duck Tours"
    },
    {
        "intDurationHour": 13,
        "intOption": null,
        "intReviewStar": 0,
        "intReviewVisitor": 0,
        "intUsdCost": 99,
        "strGuideLanguage": "Deutsch,русский,Português,中文,日本語,English,Italiano,Français,Español",
        "strImageUrl": "http://img.kkday.com/image/get/w_1024%2Cc_fit/s1.kkday.com/product_8830/20160615073259_w1vGY/jpg",
        "strIntroduction": "Take a day out of London to see the sights of beautiful Oxford! This day tour by rail will whisk you to the stunning university town in no time at all, giving you hours to explore the highlights of Oxford. This package includes a hop-on hop-off open top bus tour for fun and informative travel around the city!",
        "strLocation": "United Kingdom, Oxford",
        "strOriginUrl": "https://www.kkday.com/en/product/8830",
        "strSource": "KKDAY",
        "strStyle": null,
        "strTitle": "Day Trip to Oxford by Rail with Open Top Bus Tour"
    },
    {
        "intDurationHour": 12,
        "intOption": null,
        "intReviewStar": 0,
        "intReviewVisitor": 0,
        "intUsdCost": 60,
        "strGuideLanguage": "Español",
        "strImageUrl": "http://img.kkday.com/image/get/w_1024%2Cc_fit/s1.kkday.com/product_7002/20160325165736_Q4q4v/jpg",
        "strIntroduction": "Dunkeld on the banks of the River Tay, we expect our first stop. The small village with the remains of their abbey and cathedral were chosen by the first king of Scotland to house the relics of St. Columba. We will continue the route to Inverness, where we can see the mouth of the River Ness in the Moray Firth, the Cathedral of Saint Andrews, Inverness Castle and the university. This is the city in Scotland with higher standard of living, and the fastest growing population in recent times.",
        "strLocation": "United Kingdom, Edinburgh",
        "strOriginUrl": "https://www.kkday.com/en/product/7002",
        "strSource": "KKDAY",
        "strStyle": null,
        "strTitle": "Loch Ness and Inverness"
    },
    {
        "intDurationHour": 8,
        "intOption": null,
        "intReviewStar": 0,
        "intReviewVisitor": 0,
        "intUsdCost": 37,
        "strGuideLanguage": "Deutsch,русский,Português,中文,English,Italiano,Français,Español",
        "strImageUrl": "http://img.kkday.com/image/get/s1.kkday.com/product_8750/20160608181011_9NEvQ/jpg",
        "strIntroduction": "This convenient one day hop-on hop-off bus ticket is great for travellers planning a flying visit to the city! If you only have a single day to spare and want to see all the sights, this one day pass is for you!",
        "strLocation": "United Kingdom, London",
        "strOriginUrl": "https://www.kkday.com/en/product/8750",
        "strSource": "KKDAY",
        "strStyle": null,
        "strTitle": "1 Day Hop-On Hop-Off Bus Ticket"
    },
    {
        "intDurationHour": 10,
        "intOption": null,
        "intReviewStar": 0,
        "intReviewVisitor": 0,
        "intUsdCost": 55,
        "strGuideLanguage": "English",
        "strImageUrl": "http://img.kkday.com/image/get/w_1024%2Cc_fit/s1.kkday.com/product_1324/20160205030726_P4vTh/jpg",
        "strIntroduction": "A day spent in the land of Scots heroes Rob Roy, Robert the Bruce and William Wallace.",
        "strLocation": "United Kingdom, Edinburgh",
        "strOriginUrl": "https://www.kkday.com/en/product/1324",
        "strSource": "KKDAY",
        "strStyle": null,
        "strTitle": "Loch Lomond National Park and Stirling Castle (1 day tour)"
    },
    {
        "intDurationHour": 10,
        "intOption": null,
        "intReviewStar": 0,
        "intReviewVisitor": 0,
        "intUsdCost": 180,
        "strGuideLanguage": "English",
        "strImageUrl": "http://img.kkday.com/image/get/w_1024%2Cc_fit/s1.kkday.com/product_9268/20160714080136_ZBb2K/jpg",
        "strIntroduction": "With private viewing of Stonehenge - enter the stone circle normally out of bounds to the public. Visit Lacock and Bath, appreciate at amazing historic buildings along the streets.",
        "strLocation": "United Kingdom, London",
        "strOriginUrl": "https://www.kkday.com/en/product/9268",
        "strSource": "KKDAY",
        "strStyle": null,
        "strTitle": "Stonehenge private viewing at Sunrise"
    },
    {
        "intDurationHour": 9,
        "intOption": null,
        "intReviewStar": 0,
        "intReviewVisitor": 0,
        "intUsdCost": 55,
        "strGuideLanguage": "English",
        "strImageUrl": "http://img.kkday.com/image/get/w_1024%2Cc_fit/s1.kkday.com/product_5703/20160104034749_Dt2mC/jpg",
        "strIntroduction": "St. Andrews, the home of golf. The tour offers exploring quaint villages and ancient towns around eastern Scotland.",
        "strLocation": "United Kingdom, Edinburgh",
        "strOriginUrl": "https://www.kkday.com/en/product/5703",
        "strSource": "KKDAY",
        "strStyle": null,
        "strTitle": "Kingdoms Palaces and Golf from Edinburgh"
    },
    {
        "intDurationHour": 1,
        "intOption": null,
        "intReviewStar": 0,
        "intReviewVisitor": 0,
        "intUsdCost": 19,
        "strGuideLanguage": "Deutsch,العربية,русский,한국어,Português,中文,日本語,English,Italiano,Français,Español",
        "strImageUrl": "http://img.kkday.com/image/get/w_1024%2Cc_fit/s1.kkday.com/product_5607/20151229024542_JwCgn/jpg",
        "strIntroduction": "Immerse yourself in the ancient streets of Oxford",
        "strLocation": "United Kingdom, Oxford",
        "strOriginUrl": "https://www.kkday.com/en/product/5607",
        "strSource": "KKDAY",
        "strStyle": null,
        "strTitle": "Oxford with the City Sightseeing"
    },
    {
        "intDurationHour": 10,
        "intOption": null,
        "intReviewStar": 0,
        "intReviewVisitor": 0,
        "intUsdCost": 103,
        "strGuideLanguage": "English",
        "strImageUrl": "http://img.kkday.com/image/get/w_1024%2Cc_fit/s1.kkday.com/product_7167/20160407094736_5sshT/jpg",
        "strIntroduction": "Take a walking tour of Oxford, visit Brasenose College, and drive through Cotswolds. Explore Shakespeare’s birthplace and enjoy some time to explore Stratford-Upon-Avon. Have an extended visit of Warwick Castle and savor a Free SUBWAY Lunch.",
        "strLocation": "United Kingdom, London",
        "strOriginUrl": "https://www.kkday.com/en/product/7167",
        "strSource": "KKDAY",
        "strStyle": null,
        "strTitle": "Oxford, Stratford, Cotswolds and Warwick Castle with Free SUBWAY Lunch"
    },
    {
        "intDurationHour": 3,
        "intOption": null,
        "intReviewStar": 3,
        "intReviewVisitor": 2,
        "intUsdCost": 22,
        "strGuideLanguage": "Deutsch,한국어,中文,日本語,English,Italiano,Français,Español",
        "strImageUrl": "http://img.kkday.com/image/get/w_1024%2Cc_fit/s1.kkday.com/product_6815/20160319010300_m9JEA/jpg",
        "strIntroduction": "Skip the line and enjoy discounted fast-track entrance to the London landmark of St Paul's Cathedral. Explore the cathedral floor and crypt, climb its 3 galleries and view panoramic London from the top of the dome. Multimedia guides and tours provided.",
        "strLocation": "United Kingdom, London",
        "strOriginUrl": "https://www.kkday.com/en/product/6815",
        "strSource": "KKDAY",
        "strStyle": null,
        "strTitle": "St Paul's Cathedral Tickets - Skip the Line"
    },
    {
        "intDurationHour": 2,
        "intOption": null,
        "intReviewStar": 0,
        "intReviewVisitor": 0,
        "intUsdCost": 54,
        "strGuideLanguage": "English",
        "strImageUrl": "http://img.kkday.com/image/get/w_1024%2Cc_fit/s1.kkday.com/product_6956/20160324085615_qrCoz/jpg",
        "strIntroduction": "This musical will have all Dancing Queens hitting the dancefloor! All your favourite ABBA tunes are brought back to the stage in an all-singing and all-dancing musical.",
        "strLocation": "United Kingdom, London",
        "strOriginUrl": "https://www.kkday.com/en/product/6956",
        "strSource": "KKDAY",
        "strStyle": null,
        "strTitle": "Mamma Mia"
    },
    {
        "intDurationHour": 1,
        "intOption": null,
        "intReviewStar": 0,
        "intReviewVisitor": 0,
        "intUsdCost": 9,
        "strGuideLanguage": "English",
        "strImageUrl": "http://img.kkday.com/image/get/w_1024%2Cc_fit/s1.kkday.com/product_5699/20160204012510_y8lWC/jpg",
        "strIntroduction": "The Gallery itself is located at the Palace of Holyroodhouse, Scotland's most famous street.",
        "strLocation": "United Kingdom, Edinburgh",
        "strOriginUrl": "https://www.kkday.com/en/product/5699",
        "strSource": "KKDAY",
        "strStyle": null,
        "strTitle": "The Queens Gallery Edinburgh"
    },
    {
        "intDurationHour": 5,
        "intOption": null,
        "intReviewStar": 0,
        "intReviewVisitor": 0,
        "intUsdCost": 80,
        "strGuideLanguage": "English",
        "strImageUrl": "http://img.kkday.com/image/get/w_1024%2Cc_fit/s1.kkday.com/product_5748/20160203153049_uwXBf/jpg",
        "strIntroduction": "Follow in the footsteps of historic figures,admire opulent rooms decorated with priceless furniture with the Four Palace Royal Pass.",
        "strLocation": "United Kingdom, London",
        "strOriginUrl": "https://www.kkday.com/en/product/5748",
        "strSource": "KKDAY",
        "strStyle": null,
        "strTitle": "Four Palace Royal Pass: Tower of London, Kensington Palace, Banqueting House and Hampton Court"
    },
    {
        "intDurationHour": 3,
        "intOption": null,
        "intReviewStar": 0,
        "intReviewVisitor": 0,
        "intUsdCost": 52,
        "strGuideLanguage": "Deutsch,日本語,English,Italiano,Français,Español",
        "strImageUrl": "http://img.kkday.com/image/get/w_1024%2Cc_fit/s1.kkday.com/product_7174/20160412122205_MmcrH/jpg",
        "strIntroduction": "Go on a panoramic tour of London - see London's famous monuments including St. Paul's Cathedral and the Buckingham Palace. Plus get to see the Changing of the Guard!",
        "strLocation": "United Kingdom, London",
        "strOriginUrl": "https://www.kkday.com/en/product/7174",
        "strSource": "KKDAY",
        "strStyle": null,
        "strTitle": "Half Day Tour of London with St Paul's Cathedral and Guard Change"
    },
    {
        "intDurationHour": 720,
        "intOption": null,
        "intReviewStar": 0,
        "intReviewVisitor": 0,
        "intUsdCost": 53,
        "strGuideLanguage": "中文",
        "strImageUrl": "http://img.kkday.com/image/get/s1.kkday.com/product_9178/20160711030245_gd9A4/jpg",
        "strIntroduction": "This SIM card works in 31 different countries in Europe, provides 1250MB fast mobile internet/ data plus 300 minutes calls in 31 countries in Europe.",
        "strLocation": "United Kingdom, All city",
        "strOriginUrl": "https://www.kkday.com/en/product/9178",
        "strSource": "KKDAY",
        "strStyle": null,
        "strTitle": "30 Days Europe Prepaid Sim Card"
    },
    {
        "intDurationHour": 13,
        "intOption": null,
        "intReviewStar": 0,
        "intReviewVisitor": 0,
        "intUsdCost": 183,
        "strGuideLanguage": "English",
        "strImageUrl": "http://img.kkday.com/image/get/w_1024%2Cc_fit/s1.kkday.com/product_6829/20160321042307_bXUel/jpg",
        "strIntroduction": "Board a train and travel back in time from modern London to ancient York, the northern capital of Roman Britannia.",
        "strLocation": "United Kingdom, London",
        "strOriginUrl": "https://www.kkday.com/en/product/6829",
        "strSource": "KKDAY",
        "strStyle": null,
        "strTitle": "Day trip to York"
    },
    {
        "intDurationHour": 12,
        "intOption": null,
        "intReviewStar": 0,
        "intReviewVisitor": 0,
        "intUsdCost": 65,
        "strGuideLanguage": "Español",
        "strImageUrl": "http://img.kkday.com/image/get/w_1024%2Cc_fit/s1.kkday.com/product_7001/20160325161928_6S02D/jpg",
        "strIntroduction": "Meet hairy cows in Callander. Enjoy one of Scotland's most spectacular scenery in Glencoe. Admire the highest mountain in the UK, the Ben Nevis. Have lunch at Loch Ness. Visit also Dunkeld, the ancient capital of Scotland.",
        "strLocation": "United Kingdom, Edinburgh",
        "strOriginUrl": "https://www.kkday.com/en/product/7001",
        "strSource": "KKDAY",
        "strStyle": null,
        "strTitle": "Loch Ness and Highlands tour"
    },
    {
        "intDurationHour": 13,
        "intOption": null,
        "intReviewStar": 0,
        "intReviewVisitor": 0,
        "intUsdCost": 270,
        "strGuideLanguage": "English",
        "strImageUrl": "http://img.kkday.com/image/get/s1.kkday.com/product_7165/20160406102440_P7Vpy/jpg",
        "strIntroduction": "Edinburgh, the showcase capital city of Scotland, has one of the most beautiful cityscapes in the world—making it the perfect setting for an open top bus tour.",
        "strLocation": "United Kingdom, Edinburgh",
        "strOriginUrl": "https://www.kkday.com/en/product/7165",
        "strSource": "KKDAY",
        "strStyle": null,
        "strTitle": "Day Trip to Edinburgh (Scotland) with Edinburgh Castle & Bus Tour"
    },
    {
        "intDurationHour": 3,
        "intOption": null,
        "intReviewStar": 0,
        "intReviewVisitor": 0,
        "intUsdCost": 56,
        "strGuideLanguage": "English",
        "strImageUrl": "http://img.kkday.com/image/get/w_1024%2Cc_fit/s1.kkday.com/product_6958/20160324154430_CuK30/jpg",
        "strIntroduction": "Pay homage to the King of Pop in the most spectacular way possible at Thriller – Live, the highest-octane show in town.",
        "strLocation": "United Kingdom, London",
        "strOriginUrl": "https://www.kkday.com/en/product/6958",
        "strSource": "KKDAY",
        "strStyle": null,
        "strTitle": "Thriller - Live show"
    },
    {
        "intDurationHour": 2,
        "intOption": null,
        "intReviewStar": 0,
        "intReviewVisitor": 0,
        "intUsdCost": 21,
        "strGuideLanguage": "Deutsch,العربية,廣東話,русский,한국어,Português,中文,日本語,English,Italiano,Français,Español",
        "strImageUrl": "http://img.kkday.com/image/get/w_1024%2Cc_fit/s1.kkday.com/product_1320/20160208134857_4nYzG/jpg",
        "strIntroduction": "The Royal Yacht Britannia was home to Her Majesty The Queen and the Royal Family for over 40 years, sailing over 1,000,000 miles around the world. Now berthed in Edinburgh, you can follow in the footsteps of Royalty to discover the heart and soul of this most special of Royal residences.",
        "strLocation": "United Kingdom, Edinburgh",
        "strOriginUrl": "https://www.kkday.com/en/product/1320",
        "strSource": "KKDAY",
        "strStyle": null,
        "strTitle": "The Royal Yacht Britannia"
    },
    {
        "intDurationHour": 5,
        "intOption": null,
        "intReviewStar": 0,
        "intReviewVisitor": 0,
        "intUsdCost": 98,
        "strGuideLanguage": "English",
        "strImageUrl": "http://img.kkday.com/image/get/w_1024%2Cc_fit/s1.kkday.com/product_6819/20160321022827_BM17S/jpg",
        "strIntroduction": "Come along and build your own dream, brick by brick.",
        "strLocation": "United Kingdom, London",
        "strOriginUrl": "https://www.kkday.com/en/product/6819",
        "strSource": "KKDAY",
        "strStyle": null,
        "strTitle": "Legoland with transportation"
    },
    {
        "intDurationHour": 9,
        "intOption": null,
        "intReviewStar": 0,
        "intReviewVisitor": 0,
        "intUsdCost": 94,
        "strGuideLanguage": "English",
        "strImageUrl": "http://img.kkday.com/image/get/w_1024%2Cc_fit/s1.kkday.com/product_9339/20160720014825_AGkg2/jpg",
        "strIntroduction": "Enjoy great views of Westminster Abbey, Big Ben, the Houses of Parliament and the London Eye on our open deck vintage bus. The tour also includes a short trip on the river Thames and the chance to see the Changing of the Guard at Buckingham Palace. Then, in the afternoon, we join an independent coach tour to Stonehenge.",
        "strLocation": "United Kingdom, London",
        "strOriginUrl": "https://www.kkday.com/en/product/9339",
        "strSource": "KKDAY",
        "strStyle": null,
        "strTitle": "Open Top London Bus tour with Afternoon Visit to Stonehenge"
    },
    {
        "intDurationHour": 10,
        "intOption": null,
        "intReviewStar": 0,
        "intReviewVisitor": 0,
        "intUsdCost": 107,
        "strGuideLanguage": "English",
        "strImageUrl": "http://img.kkday.com/image/get/w_1024%2Cc_fit/s1.kkday.com/product_7160/20160407095458_KEx2j/jpg",
        "strIntroduction": "Enjoy a full day discovering the treasures of Kent, including visits to romantic Leeds Castle, historic Canterbury Cathedral, the dramatic White Cliffs of Dover, and the legendary Greenwich Meridian.",
        "strLocation": "United Kingdom, London",
        "strOriginUrl": "https://www.kkday.com/en/product/7160",
        "strSource": "KKDAY",
        "strStyle": null,
        "strTitle": "Leeds Castle, Canterbury, Dover & Greenwich River Boat Ride with Free SUBWAY Lunch"
    },
    {
        "intDurationHour": 10,
        "intOption": null,
        "intReviewStar": 0,
        "intReviewVisitor": 0,
        "intUsdCost": 64,
        "strGuideLanguage": "Español",
        "strImageUrl": "http://img.kkday.com/image/get/w_1024%2Cc_fit/s1.kkday.com/product_6998/20160325102809_wVrVX/jpg",
        "strIntroduction": "Travel deep into the soul of Scotland with this fascinating tour that explores the country’s history, culture and landscapes. Discover the stunning Stirling Castle, behold the wonderful Wallace Monument, head to a whisky distillery, visit St Andrews, the spiritual home of golf and location of Scotland’s most prestigious university, and see one of the world’s most impressive bridges.",
        "strLocation": "United Kingdom, Edinburgh",
        "strOriginUrl": "https://www.kkday.com/en/product/6998",
        "strSource": "KKDAY",
        "strStyle": null,
        "strTitle": "Stirling Castle, whisky distillery and St Andrews"
    },
    {
        "intDurationHour": 10,
        "intOption": null,
        "intReviewStar": 0,
        "intReviewVisitor": 0,
        "intUsdCost": 1,
        "strGuideLanguage": "中文",
        "strImageUrl": "http://img.kkday.com/image/get/w_1024%2Cc_fit/s1.kkday.com/product_3862/20160206161433_CzsNR/jpg",
        "strIntroduction": "Guests will be picked up from London Downtown and taken to the following attractions: Big Ben, Tower Bridge, The London Eye, Thames River, British Museum, Houses of Parliament, St Paul's Cathedral, Westminster Abbey, Regent's Park, No.10 Downng Street, Whitehall Street, St James Park, Buckingham Palace, China Town, National Gallery, The Royal Observatory Greenwich, The Prime Meridian, Clock Tower of the Old Royal Observatory, Covent Garden, Madame Tussauds London, Hyde Park, and Kensington Gardens.",
        "strLocation": "United Kingdom, London",
        "strOriginUrl": "https://www.kkday.com/en/product/3862",
        "strSource": "KKDAY",
        "strStyle": null,
        "strTitle": "Private Customized Tour in London"
    },
    {
        "intDurationHour": 5,
        "intOption": null,
        "intReviewStar": 0,
        "intReviewVisitor": 0,
        "intUsdCost": 76,
        "strGuideLanguage": "English",
        "strImageUrl": "http://img.kkday.com/image/get/w_1024%2Cc_fit/s1.kkday.com/product_7170/20160408025717_3oSeC/jpg",
        "strIntroduction": "London is well-known around the world for being the main home of England’s fascinating monarchy. If you can’t get enough of the Royals or are fascinated by the history of the monarchy, this tour is for you! You’ll enjoy special timed entry to Buckingham Palace, a visit to St. Paul’s Cathedral and a panoramic tour of the capital during this morning package.",
        "strLocation": "United Kingdom, London",
        "strOriginUrl": "https://www.kkday.com/en/product/7170",
        "strSource": "KKDAY",
        "strStyle": null,
        "strTitle": "Royal London Tour with visit inside Buckingham Palace & Changing of the Guard"
    },
    {
        "intDurationHour": 11,
        "intOption": null,
        "intReviewStar": 0,
        "intReviewVisitor": 0,
        "intUsdCost": 65,
        "strGuideLanguage": "English",
        "strImageUrl": "http://img.kkday.com/image/get/w_1024%2Cc_fit/s1.kkday.com/product_1339/20150527062125_IjoI5/jpg",
        "strIntroduction": "Departing from Edinburgh, you will travel South on old Roman Dere Street that linked the supply ports on the South of England with the ancient City of York, and North past Hadrian's Wall to the Roman settlements in Central Scotland.",
        "strLocation": "United Kingdom, Edinburgh",
        "strOriginUrl": "https://www.kkday.com/en/product/1339",
        "strSource": "KKDAY",
        "strStyle": null,
        "strTitle": "Hadrian’s Wall & Scottish Borders ( 1 day tour )"
    },
    {
        "intDurationHour": 10,
        "intOption": null,
        "intReviewStar": 0,
        "intReviewVisitor": 0,
        "intUsdCost": 68,
        "strGuideLanguage": "Italiano,Français,Español",
        "strImageUrl": "http://img.kkday.com/image/get/s1.kkday.com/product_7016/20160326155244_OZfWI/jpg",
        "strIntroduction": "We will take a panoramic tour of Glasgow, including its cathedral. We will then visit Loch Lomond, where you may choose to board for a pleasant cruise. Alternatively, you can opt for a walk along the bank to Balloch Castle. You will also admire Loch Katrine, considered the most beautiful in Scotland. Finally, we will discover Doune Castle and the William Wallace monument.",
        "strLocation": "United Kingdom, Edinburgh",
        "strOriginUrl": "https://www.kkday.com/en/product/7016",
        "strSource": "KKDAY",
        "strStyle": null,
        "strTitle": "Glasgow, Lochs Lomond and Katrine and Doune Castle tour"
    },
    {
        "intDurationHour": 11,
        "intOption": null,
        "intReviewStar": 0,
        "intReviewVisitor": 0,
        "intUsdCost": 79,
        "strGuideLanguage": "English,Español",
        "strImageUrl": "http://img.kkday.com/image/get/w_1024%2Cc_fit/s1.kkday.com/product_6812/20160318153921_CTekD/jpg",
        "strIntroduction": "The legends and lore of Olde England come to life with this compelling full day tour.",
        "strLocation": "United Kingdom, London",
        "strOriginUrl": "https://www.kkday.com/en/product/6812",
        "strSource": "KKDAY",
        "strStyle": null,
        "strTitle": "Bath, Stonehenge and Salisbury tour"
    },
    {
        "intDurationHour": 3,
        "intOption": null,
        "intReviewStar": 0,
        "intReviewVisitor": 0,
        "intUsdCost": 30,
        "strGuideLanguage": "English",
        "strImageUrl": "http://img.kkday.com/image/get/w_1024%2Cc_fit/s1.kkday.com/product_5714/20160202104102_xHBWC/jpg",
        "strIntroduction": "See the highlights of the British Museum on a 2-hour guided tour, and discover relics from Ancient Egypt to artifacts.",
        "strLocation": "United Kingdom, London",
        "strOriginUrl": "https://www.kkday.com/en/product/5714",
        "strSource": "KKDAY",
        "strStyle": null,
        "strTitle": "British Museum highlights tour"
    },
    {
        "intDurationHour": 10,
        "intOption": null,
        "intReviewStar": 0,
        "intReviewVisitor": 0,
        "intUsdCost": 111,
        "strGuideLanguage": "English",
        "strImageUrl": "http://img.kkday.com/image/get/w_1024%2Cc_fit/s1.kkday.com/product_8892/20160618102442_XCocP/jpg",
        "strIntroduction": "Visit Burford, Bibury and Northern Cotswolds. Marvel at the view of the most beautiful village in England and have a unforgettable lunch.",
        "strLocation": "United Kingdom, London",
        "strOriginUrl": "https://www.kkday.com/en/product/8892",
        "strSource": "KKDAY",
        "strStyle": null,
        "strTitle": "Lunch in the Cotswolds with lunch in the prettiest village in Britain"
    },
    {
        "intDurationHour": 2,
        "intOption": null,
        "intReviewStar": 0,
        "intReviewVisitor": 0,
        "intUsdCost": 31,
        "strGuideLanguage": "Deutsch,العربية,русский,Português,中文,日本語,English,Italiano,Français",
        "strImageUrl": "http://img.kkday.com/image/get/w_1024%2Cc_fit/s1.kkday.com/product_6759/20160316164252_gqSBJ/jpg",
        "strIntroduction": "Go behind the scenes at Arsenal Football Club on this combined Emirates Stadium tour and Arsenal Museum visit. Take your seat in the changing room, walk down the players’ tunnel, sit in the dugout, and imagine the roar of 60,000 fans.",
        "strLocation": "United Kingdom, London",
        "strOriginUrl": "https://www.kkday.com/en/product/6759",
        "strSource": "KKDAY",
        "strStyle": null,
        "strTitle": "90 Minute Emirates Stadium Tour and Arsenal Museum"
    },
    {
        "intDurationHour": 10,
        "intOption": null,
        "intReviewStar": 0,
        "intReviewVisitor": 0,
        "intUsdCost": 125,
        "strGuideLanguage": "English,Español",
        "strImageUrl": "http://img.kkday.com/image/get/w_1024%2Cc_fit/s1.kkday.com/product_6817/20160319133538_nxG2G/jpg",
        "strIntroduction": "Escape London for the beautiful Kent countryside with this full day tour taking in Leeds Castle, the cathedral city of Canterbury, the famous White Cliffs of Dover and Greenwich before returning to the capital aboard a river cruiser.",
        "strLocation": "United Kingdom, London",
        "strOriginUrl": "https://www.kkday.com/en/product/6817",
        "strSource": "KKDAY",
        "strStyle": null,
        "strTitle": "Leeds Castle, Canterbury, Cliffs of Dover and Greenwich Tour with Thames cruise"
    },
    {
        "intDurationHour": 2,
        "intOption": null,
        "intReviewStar": 0,
        "intReviewVisitor": 0,
        "intUsdCost": 27,
        "strGuideLanguage": "English",
        "strImageUrl": "http://img.kkday.com/image/get/w_1024%2Cc_fit/s1.kkday.com/product_9458/20160727082041_RBvTC/jpg",
        "strIntroduction": "An absolutely essential part of any visit to London, Westminster Abbey is one of the city’s most iconic buildings. With your ticket, explore a thousand years of history and marvel at the exquisite Gothic architecture and beautiful stained glass.",
        "strLocation": "United Kingdom, London",
        "strOriginUrl": "https://www.kkday.com/en/product/9458",
        "strSource": "KKDAY",
        "strStyle": null,
        "strTitle": "London Westminster Abbey Entrance Ticket & Audio Guide"
    },
    {
        "intDurationHour": 12,
        "intOption": null,
        "intReviewStar": 0,
        "intReviewVisitor": 0,
        "intUsdCost": 137,
        "strGuideLanguage": "English",
        "strImageUrl": "http://img.kkday.com/image/get/w_1024%2Cc_fit/s1.kkday.com/product_7168/20160614094259_y50MD/jpg",
        "strIntroduction": "See the remarkable prehistoric monument of Stonehenge and learn about its amazing history on this private full-day tour from London. Visit this UNESCO World Heritage Site and enjoy direct access to the historic stone formation as the sun sets.",
        "strLocation": "United Kingdom, London",
        "strOriginUrl": "https://www.kkday.com/en/product/7168",
        "strSource": "KKDAY",
        "strStyle": null,
        "strTitle": "Private Viewing of Stonehenge (access to the stone circle) and the Roman Baths"
    },
    {
        "intDurationHour": 3,
        "intOption": null,
        "intReviewStar": 0,
        "intReviewVisitor": 0,
        "intUsdCost": 38,
        "strGuideLanguage": "English",
        "strImageUrl": "http://img.kkday.com/image/get/w_1024%2Cc_fit/s1.kkday.com/product_6953/20160324080618_0F8xL/jpg",
        "strIntroduction": "You’ll be left wanting more with this spectacular one-of-a-kind musical dubbed the musical of the decade.",
        "strLocation": "United Kingdom, London",
        "strOriginUrl": "https://www.kkday.com/en/product/6953",
        "strSource": "KKDAY",
        "strStyle": null,
        "strTitle": "Wicked The Musical"
    },
    {
        "intDurationHour": 2,
        "intOption": null,
        "intReviewStar": 0,
        "intReviewVisitor": 0,
        "intUsdCost": 33,
        "strGuideLanguage": "English",
        "strImageUrl": "http://img.kkday.com/image/get/w_1024%2Cc_fit/s1.kkday.com/product_6987/20160325084413_9aTry/jpg",
        "strIntroduction": "MBNA Thames Clippers and Emirates Air Line have joined together to create exclusive joint packages to fly over and glide down the Thames; the two most unique ways to travel in London.",
        "strLocation": "United Kingdom, London",
        "strOriginUrl": "https://www.kkday.com/en/product/6987",
        "strSource": "KKDAY",
        "strStyle": null,
        "strTitle": "Emirates Air Line and MBNA Thames Clippers"
    },
    {
        "intDurationHour": 0,
        "intOption": null,
        "intReviewStar": 0,
        "intReviewVisitor": 0,
        "intUsdCost": 45,
        "strGuideLanguage": "Deutsch,日本語,English,Français,Español",
        "strImageUrl": "http://img.kkday.com/image/get/w_1024%2Cc_fit/s1.kkday.com/product_6058/20160206064041_kw0oQ/jpg",
        "strIntroduction": "Rub elbows with your favourite celebrities and snap a souvenir photo with legends at the one and only Madame Tussauds.",
        "strLocation": "United Kingdom, London",
        "strOriginUrl": "https://www.kkday.com/en/product/6058",
        "strSource": "KKDAY",
        "strStyle": null,
        "strTitle": "Madame Tussauds London and Marvel 4D"
    },
    {
        "intDurationHour": 3,
        "intOption": null,
        "intReviewStar": 0,
        "intReviewVisitor": 0,
        "intUsdCost": 36,
        "strGuideLanguage": "English",
        "strImageUrl": "http://img.kkday.com/image/get/s1.kkday.com/product_9175/20160711020118_sl3uB/jpg",
        "strIntroduction": "Travel back in time on a vintage open top double-decker bus, and walk through an empty Smithfield market, home to the cock-lane Ghost. Then retrace the murder sites of Jack the Ripper, before heading to the safety of the Sherlock Holmes pub.",
        "strLocation": "United Kingdom, London",
        "strOriginUrl": "https://www.kkday.com/en/product/9175",
        "strSource": "KKDAY",
        "strStyle": null,
        "strTitle": "Jack the Ripper, Haunted London and Sherlock Holmes Tour"
    },
    {
        "intDurationHour": 4,
        "intOption": null,
        "intReviewStar": 0,
        "intReviewVisitor": 0,
        "intUsdCost": 182,
        "strGuideLanguage": "English",
        "strImageUrl": "http://img.kkday.com/image/get/w_1024%2Cc_fit/s1.kkday.com/product_6951/20160324071403_1cB0C/jpg",
        "strIntroduction": "Get to grips with Britain’s royal and political history on this 4-hour tour of Westminster Abbey and the Houses of Parliament. Step inside the famous Gothic abbey, which has been the setting for almost all English coronations since William the Conqueror’s crowning in 1066, along with many other royal occasions including Prince William and Kate Middleton’s wedding. Then gain insight into the British political system with a guided tour of the House of Lords and Houses of Commons inside the Houses of Parliament.",
        "strLocation": "United Kingdom, London",
        "strOriginUrl": "https://www.kkday.com/en/product/6951",
        "strSource": "KKDAY",
        "strStyle": null,
        "strTitle": "Behind the Scenes Tour: Parliament, Westminster Abbey and Big Ben"
    },
    {
        "intDurationHour": 2,
        "intOption": null,
        "intReviewStar": 0,
        "intReviewVisitor": 0,
        "intUsdCost": 333,
        "strGuideLanguage": "English",
        "strImageUrl": "http://img.kkday.com/image/get/s1.kkday.com/product_6776/20160318033022_mPnVl/jpg",
        "strIntroduction": "Find out what makes London really swing in a restored classic Mini Cooper with your very own passionate local guide to bring the city to life. See not only the iconic sights of the capital but also discover the hidden gems that are often overlooked.",
        "strLocation": "United Kingdom, London",
        "strOriginUrl": "https://www.kkday.com/en/product/6776",
        "strSource": "KKDAY",
        "strStyle": null,
        "strTitle": "Private Sightseeing Tour of London in Classic Mini Cooper: Best Bits of London"
    },
    {
        "intDurationHour": 5,
        "intOption": null,
        "intReviewStar": 0,
        "intReviewVisitor": 0,
        "intUsdCost": 43,
        "strGuideLanguage": "中文,English",
        "strImageUrl": "http://img.kkday.com/image/get/w_1024%2Cc_fit/s1.kkday.com/product_6902/20160322101402_vyNPO/jpg",
        "strIntroduction": "For a non-stop adrenaline rush, grab your mates and experience some of Europe’s most extreme rides, the UK’s most exciting evening entertainment and the ultimate overnight stay - all at the nation’s Thrill Capital, THORPE PARK",
        "strLocation": "United Kingdom, London",
        "strOriginUrl": "https://www.kkday.com/en/product/6902",
        "strSource": "KKDAY",
        "strStyle": null,
        "strTitle": "Thorpe Park Tickets"
    },
    {
        "intDurationHour": 0,
        "intOption": null,
        "intReviewStar": 0,
        "intReviewVisitor": 0,
        "intUsdCost": 64,
        "strGuideLanguage": "English",
        "strImageUrl": "http://img.kkday.com/image/get/w_1024%2Cc_fit/s1.kkday.com/product_6085/20160214140659_Dn86Z/jpg",
        "strIntroduction": "This fast paced Thames Barrier Voyage takes you on an adventure journey through the amazing Thames Barrier, the “eighth wonder of the world”",
        "strLocation": "United Kingdom, London",
        "strOriginUrl": "https://www.kkday.com/en/product/6085",
        "strSource": "KKDAY",
        "strStyle": null,
        "strTitle": "Speed Boat Ride Thames Jet"
    },
    {
        "intDurationHour": 2,
        "intOption": null,
        "intReviewStar": 0,
        "intReviewVisitor": 0,
        "intUsdCost": 16,
        "strGuideLanguage": "English",
        "strImageUrl": "http://img.kkday.com/image/get/s1.kkday.com/product_7045/20160328072038_8bstY/jpg",
        "strIntroduction": "You can visit the Palace of Holyroodhouse at your leisure using the complimentary audio tour, which lasts approximately 1 hour.",
        "strLocation": "United Kingdom, Edinburgh",
        "strOriginUrl": "https://www.kkday.com/en/product/7045",
        "strSource": "KKDAY",
        "strStyle": null,
        "strTitle": "Palace of Holyrood house"
    },
    {
        "intDurationHour": 8,
        "intOption": null,
        "intReviewStar": 0,
        "intReviewVisitor": 0,
        "intUsdCost": 26,
        "strGuideLanguage": "English",
        "strImageUrl": "http://img.kkday.com/image/get/w_1024%2Cc_fit/s1.kkday.com/product_5716/20160203234736_QPkpk/jpg",
        "strIntroduction": "Come and live Britain's greatest medieval experience at the wonderfully preserved Warwick Castle.",
        "strLocation": "United Kingdom, London",
        "strOriginUrl": "https://www.kkday.com/en/product/5716",
        "strSource": "KKDAY",
        "strStyle": null,
        "strTitle": "Warwick Castle medieval experience"
    },
    {
        "intDurationHour": 0,
        "intOption": null,
        "intReviewStar": 0,
        "intReviewVisitor": 0,
        "intUsdCost": 26,
        "strGuideLanguage": "Deutsch,Português,中文,日本語,English,Italiano,Français,Español",
        "strImageUrl": "http://img.kkday.com/image/get/w_1024%2Cc_fit/s1.kkday.com/product_6064/20160207121005_3XFQd/jpg",
        "strIntroduction": "The award-winning the Beatles Story is the world's largest permanent exhibition purely devoted to the lives and times of The Beatles. Located in the Fab Four’s hometown of Liverpool on the stunning UNESCO World heritage site at the Albert Dock.",
        "strLocation": "United Kingdom, Liverpool",
        "strOriginUrl": "https://www.kkday.com/en/product/6064",
        "strSource": "KKDAY",
        "strStyle": null,
        "strTitle": "The Beatles Story Museum"
    },
    {
        "intDurationHour": 2,
        "intOption": null,
        "intReviewStar": 0,
        "intReviewVisitor": 0,
        "intUsdCost": 25,
        "strGuideLanguage": "English",
        "strImageUrl": "http://img.kkday.com/image/get/w_1024%2Cc_fit/s1.kkday.com/product_6034/20160202125041_PvhgB/jpg",
        "strIntroduction": "Come and enjoy one of the four delicious menus that are as legendary as the music and venue itself.",
        "strLocation": "United Kingdom, London",
        "strOriginUrl": "https://www.kkday.com/en/product/6034",
        "strSource": "KKDAY",
        "strStyle": null,
        "strTitle": "Hard Rock Cafe Manchester London – Skip the line"
    },
    {
        "intDurationHour": 144,
        "intOption": null,
        "intReviewStar": 0,
        "intReviewVisitor": 0,
        "intUsdCost": 99,
        "strGuideLanguage": "Deutsch,English,Italiano,Français,Español",
        "strImageUrl": "http://img.kkday.com/image/get/w_1024%2Cc_fit/s1.kkday.com/product_6910/20160322150038_PFV5n/jpg",
        "strIntroduction": "The Oyster Travelcard comes with a pre-loaded credit/value related to the duration of your London Pass. Learn more about how much credit you get with your Oyster Travelcard and how easy it is to make savings on a daily basis while travelling around London's zones.",
        "strLocation": "United Kingdom, London",
        "strOriginUrl": "https://www.kkday.com/en/product/6910",
        "strSource": "KKDAY",
        "strStyle": null,
        "strTitle": "London Pass Including Oyster Travel Card"
    },
    {
        "intDurationHour": 4,
        "intOption": null,
        "intReviewStar": 0,
        "intReviewVisitor": 0,
        "intUsdCost": 72,
        "strGuideLanguage": "English",
        "strImageUrl": "http://img.kkday.com/image/get/w_1024%2Cc_fit/s1.kkday.com/product_5719/20160204084232_04txC/jpg",
        "strIntroduction": "Step inside magnificent Buckingham Palace and explore the rooms used by the Royals before enjoying traditional afternoon tea with this first-class",
        "strLocation": "United Kingdom, London",
        "strOriginUrl": "https://www.kkday.com/en/product/5719",
        "strSource": "KKDAY",
        "strStyle": null,
        "strTitle": "Buckingham Palace and afternoon tea"
    },
    {
        "intDurationHour": 10,
        "intOption": null,
        "intReviewStar": 0,
        "intReviewVisitor": 0,
        "intUsdCost": 157,
        "strGuideLanguage": "English",
        "strImageUrl": "http://img.kkday.com/image/get/w_1024%2Cc_fit/s1.kkday.com/product_7161/20160412151330_CLxjO/jpg",
        "strIntroduction": "Explore the mysterious Stonehenge, the Cathedral housing Magna Carta, and the hot-spring fed Roman Bath.",
        "strLocation": "United Kingdom, London",
        "strOriginUrl": "https://www.kkday.com/en/product/7161",
        "strSource": "KKDAY",
        "strStyle": null,
        "strTitle": "Bath, Stonehenge and Salisbury with Free SUBWAY Lunch"
    },
    {
        "intDurationHour": 2,
        "intOption": null,
        "intReviewStar": 0,
        "intReviewVisitor": 0,
        "intUsdCost": 21,
        "strGuideLanguage": "",
        "strImageUrl": "http://img.kkday.com/image/get/w_1024%2Cc_fit/s1.kkday.com/product_9449/20160727063150_PlrDT/jpg",
        "strIntroduction": "Book your timed admission ticket for Stonehenge, one of the world’s most famous prehistoric monuments. When you visit the site you’ll be able to explore its new world-class visitor center that houses museum-quality exhibits, a shop, and a café.",
        "strLocation": "United Kingdom, London",
        "strOriginUrl": "https://www.kkday.com/en/product/9449",
        "strSource": "KKDAY",
        "strStyle": null,
        "strTitle": "Stonehenge Admission Ticket"
    },
    {
        "intDurationHour": 1,
        "intOption": null,
        "intReviewStar": 5,
        "intReviewVisitor": 83,
        "intUsdCost": 125,
        "strGuideLanguage": "中文,English",
        "strImageUrl": "http://img.kkday.com/image/get/w_1024%2Cc_fit/s1.kkday.com/product_3598/20160506100756_dMg7m/jpg",
        "strIntroduction": "무제한 (LTE) 초고속 인터넷! 한기기로 최소 5명이상 공유가능. 맛집 찾으면서 대만여행을 즐기세요! 데이터 요금 걱정없이 카톡, 인터넷, 길찾기 등을 자유롭게 사용하세요.",
        "strLocation": "대만, 까오슝, 타오위엔, 타이베이",
        "strOriginUrl": "https://www.kkday.com/en/product/7993",
        "strSource": "KKDAY",
        "strStyle": null,
        "strTitle": "대만 LTE 포켓와이파이 (송산 공항, 타오위안 국제공항, 가오슝 공항에서 수령반납 )"
    },
    {
        "intDurationHour": 2,
        "intOption": null,
        "intReviewStar": 0,
        "intReviewVisitor": 0,
        "intUsdCost": 47,
        "strGuideLanguage": "English",
        "strImageUrl": "http://img.kkday.com/image/get/w_1024%2Cc_fit/s1.kkday.com/product_7960/20160508163909_MCGh5/jpg",
        "strIntroduction": "This one of a kind Venice Walking Tour is the ideal Venice city sightseeing tour for the first time visitor!",
        "strLocation": "Italy, Venice",
        "strOriginUrl": "https://www.kkday.com/en/product/7960",
        "strSource": "KKDAY",
        "strStyle": null,
        "strTitle": "Small Group Essence of Venice Walk"
    },
    {
        "intDurationHour": 13,
        "intOption": null,
        "intReviewStar": 0,
        "intReviewVisitor": 0,
        "intUsdCost": 186,
        "strGuideLanguage": "Deutsch,English,Español",
        "strImageUrl": "http://img.kkday.com/image/get/w_1024%2Cc_fit/s1.kkday.com/product_6457/20160228034930_s4OjC/jpg",
        "strIntroduction": "Make the most of your holiday in Rome and take a day trip to picture postcard Florence.",
        "strLocation": "Italy, Florence",
        "strOriginUrl": "https://www.kkday.com/en/product/6457",
        "strSource": "KKDAY",
        "strStyle": null,
        "strTitle": "A Day in Florence from Rome"
    },
    {
        "intDurationHour": 9,
        "intOption": null,
        "intReviewStar": 5,
        "intReviewVisitor": 2,
        "intUsdCost": 90,
        "strGuideLanguage": "Deutsch,English,Italiano,Français,Español",
        "strImageUrl": "http://img.kkday.com/image/get/w_1024%2Cc_fit/s1.kkday.com/product_1164/20150525080716_GRIy2/jpg",
        "strIntroduction": "Enjoy the charm of the Chianti countryside, one of the most beautiful areas of Tuscany, known all over the world not only for its famous wine, but also for its landscapes and vineyards, olive trees and cypresses surrounding churches, castles and villages hidden in the hills. In the heart of Chianti we visit a famous Winery with Castle, led by a winemaker in the historic cellars where the famous barrels of Chianti Classico are kept.",
        "strLocation": "Italy, Florence",
        "strOriginUrl": "https://www.kkday.com/en/product/1164",
        "strSource": "KKDAY",
        "strStyle": null,
        "strTitle": "Best of classic Chianti with wine tasting"
    },
    {
        "intDurationHour": 16,
        "intOption": null,
        "intReviewStar": 0,
        "intReviewVisitor": 0,
        "intUsdCost": 227,
        "strGuideLanguage": "English,Español",
        "strImageUrl": "http://img.kkday.com/image/get/w_1024%2Cc_fit/s1.kkday.com/product_6442/20160227145400_Go9Oh/jpeg",
        "strIntroduction": "Travel from Rome to the enchanting city of Venice. Built on a lagoon, connected by canals and bridges, this is a city that exudes romance.",
        "strLocation": "Italy, Venice",
        "strOriginUrl": "https://www.kkday.com/en/product/6442",
        "strSource": "KKDAY",
        "strStyle": null,
        "strTitle": "Romantic Venice by train"
    },
    {
        "intDurationHour": 4,
        "intOption": null,
        "intReviewStar": 0,
        "intReviewVisitor": 0,
        "intUsdCost": 24,
        "strGuideLanguage": "Deutsch,English,Italiano,Français,Español",
        "strImageUrl": "http://img.kkday.com/image/get/w_1024%2Cc_fit/s1.kkday.com/product_7091/20160330070131_AQJe1/jpg",
        "strIntroduction": "Discover the lagoon islands of Murano, Burano and Torcello and learn more about Venice and its ancient way of life.",
        "strLocation": "Italy, Venice",
        "strOriginUrl": "https://www.kkday.com/en/product/7091",
        "strSource": "KKDAY",
        "strStyle": null,
        "strTitle": "Tour to the Islands of Burano, Murano and Torcello"
    },
    {
        "intDurationHour": 6,
        "intOption": null,
        "intReviewStar": 0,
        "intReviewVisitor": 0,
        "intUsdCost": 128,
        "strGuideLanguage": "English",
        "strImageUrl": "http://img.kkday.com/image/get/w_1024%2Cc_fit/s1.kkday.com/product_6438/20160227123943_BtW3g/jpg",
        "strIntroduction": "Reveal the beauty of the Tuscan countryside, giving you the opportunity to explore it on horseback. Enjoy lunch at a 17th-century villa.",
        "strLocation": "Italy, Florence",
        "strOriginUrl": "https://www.kkday.com/en/product/6438",
        "strSource": "KKDAY",
        "strStyle": null,
        "strTitle": "Horses and Vineyards - Horseback riding in Tuscany"
    },
    {
        "intDurationHour": 3,
        "intOption": null,
        "intReviewStar": 4,
        "intReviewVisitor": 2,
        "intUsdCost": 67,
        "strGuideLanguage": "English",
        "strImageUrl": "http://img.kkday.com/image/get/w_1024%2Cc_fit/s1.kkday.com/product_1142/20150525083351_2BNkL/jpg",
        "strIntroduction": "Frascati Wine Tasting Tour is Rome's only group wine tasting tour to visit the Frascati Region. The best of Italy lies just an hour outside of Rome. The beautiful Frascati Region is home to forested hills, stunning castles and incredible lakes. The wine estate visited on this tour was specially chosen as it is the oldest and most beautiful in the area.",
        "strLocation": "Italy, Rome",
        "strOriginUrl": "https://www.kkday.com/en/product/1142",
        "strSource": "KKDAY",
        "strStyle": null,
        "strTitle": "Frascati Wine tasting tour"
    },
    {
        "intDurationHour": 3,
        "intOption": null,
        "intReviewStar": 0,
        "intReviewVisitor": 0,
        "intUsdCost": 62,
        "strGuideLanguage": "English",
        "strImageUrl": "http://img.kkday.com/image/get/s1.kkday.com/product_7957/20160530115241_Ssbmt/jpg",
        "strIntroduction": "This tour combines our Original Venice Walking Tour with a Venice Gondola Ride to give you the best value!",
        "strLocation": "Italy, Venice",
        "strOriginUrl": "https://www.kkday.com/en/product/7957",
        "strSource": "KKDAY",
        "strStyle": null,
        "strTitle": "Original Walk and Gondola Ride Special Offer"
    },
    {
        "intDurationHour": 3,
        "intOption": null,
        "intReviewStar": 5,
        "intReviewVisitor": 1,
        "intUsdCost": 9,
        "strGuideLanguage": "",
        "strImageUrl": "http://img.kkday.com/image/get/s1.kkday.com/product_4570/20160202090648_I8nBL/jpg",
        "strIntroduction": "高品質上網分享器，給您在國外網路也能暢通無阻的體驗！取機還機超方便。高品質上網分享器，給您在國外網路也能暢通無阻的體驗！",
        "strLocation": "Italy, All city",
        "strOriginUrl": "https://www.kkday.com/en/product/4570",
        "strSource": "KKDAY",
        "strStyle": null,
        "strTitle": "Europe Pocket WiFi"
    },
    {
        "intDurationHour": 12,
        "intOption": null,
        "intReviewStar": 0,
        "intReviewVisitor": 0,
        "intUsdCost": 88,
        "strGuideLanguage": "Deutsch,русский,Português,中文,日本語,English,Italiano,Français,Español",
        "strImageUrl": "http://img.kkday.com/image/get/s1.kkday.com/product_1149/20160519071530_cJn1b/jpg",
        "strIntroduction": "See the best and most beautiful spots that Tuscany has to offer with this one day tour to Pisa, San Gimignano and Sienna.",
        "strLocation": "Italy, Florence",
        "strOriginUrl": "https://www.kkday.com/en/product/1149",
        "strSource": "KKDAY",
        "strStyle": null,
        "strTitle": "Tuscany in a Day"
    },
    {
        "intDurationHour": 4,
        "intOption": null,
        "intReviewStar": 0,
        "intReviewVisitor": 0,
        "intUsdCost": 44,
        "strGuideLanguage": "English",
        "strImageUrl": "http://img.kkday.com/image/get/w_1024%2Cc_fit/s1.kkday.com/product_1546/20150525075839_CUJFS/jpg",
        "strIntroduction": "",
        "strLocation": "Italy, Taormina",
        "strOriginUrl": "https://www.kkday.com/en/product/1546",
        "strSource": "KKDAY",
        "strStyle": null,
        "strTitle": "'The Godfather' Movie Tour from Taormina"
    },
    {
        "intDurationHour": 5,
        "intOption": null,
        "intReviewStar": 0,
        "intReviewVisitor": 0,
        "intUsdCost": 30,
        "strGuideLanguage": "Deutsch,English,Italiano,Français,Español",
        "strImageUrl": "http://img.kkday.com/image/get/w_1024%2Cc_fit/s1.kkday.com/product_1351/20160427095756_Wf5Vd/jpg",
        "strIntroduction": "Attend a Papal Audience with Pope Francis I at the Vatican! Tickets may be free but they are extremely hard to come by, so booking in advance is essential. By booking ahead, you're ensuring you won't waste any time trying to get tickets while you're on vacation in the Eternal City.",
        "strLocation": "Italy, Rome",
        "strOriginUrl": "https://www.kkday.com/en/product/1351",
        "strSource": "KKDAY",
        "strStyle": null,
        "strTitle": "Papal Audience in Rome"
    },
    {
        "intDurationHour": 5,
        "intOption": null,
        "intReviewStar": 0,
        "intReviewVisitor": 0,
        "intUsdCost": 69,
        "strGuideLanguage": "English",
        "strImageUrl": "http://img.kkday.com/image/get/w_1024%2Cc_fit/s1.kkday.com/product_1167/20160415095109_g37F5/jpg",
        "strIntroduction": "Learn time-honoured recipes and techniques for cooking authentic Italian pastry.",
        "strLocation": "Italy, Florence",
        "strOriginUrl": "https://www.kkday.com/en/product/1167",
        "strSource": "KKDAY",
        "strStyle": null,
        "strTitle": "Pastry Cooking Class"
    },
    {
        "intDurationHour": 2,
        "intOption": null,
        "intReviewStar": 4,
        "intReviewVisitor": 2,
        "intUsdCost": 135,
        "strGuideLanguage": "English,Italiano",
        "strImageUrl": "http://img.kkday.com/image/get/w_1024%2Cc_fit/s1.kkday.com/product_1466/20150525100233_qMpeZ/jpg",
        "strIntroduction": "For your Venetian Rowing Lesson, we’ll first introduce you to our traditional batelina, once one of the most prolific in the city. Now extremely rare, they make an exceptional first time rowing boat: stable and comfortable.",
        "strLocation": "Italy, Venice",
        "strOriginUrl": "https://www.kkday.com/en/product/1466",
        "strSource": "KKDAY",
        "strStyle": null,
        "strTitle": "Venice Gondola School: Learn How to Be a Gondolier"
    },
    {
        "intDurationHour": 4,
        "intOption": null,
        "intReviewStar": 0,
        "intReviewVisitor": 0,
        "intUsdCost": 88,
        "strGuideLanguage": "Deutsch,English",
        "strImageUrl": "http://img.kkday.com/image/get/w_1024%2Cc_fit/s1.kkday.com/product_1103/20160415080759_KuFhl/jpg",
        "strIntroduction": "Take a bite out of three of Rome’s tastiest neighbourhoods with this foodie tour through the enchanting squares and cobbled streets Campo de Fiori, the former Jewish Ghetto and Trastevere. This is a great opportunity to get an insider’s view of really authentic Italian cuisine and learn about the country's delectable wines on this alluring food tour of Rome s most famed areas for foodies.",
        "strLocation": "Italy, Rome",
        "strOriginUrl": "https://www.kkday.com/en/product/1103",
        "strSource": "KKDAY",
        "strStyle": null,
        "strTitle": "Food tour of Campo de Fiori, Jewish Ghetto and Trastevere"
    },
    {
        "intDurationHour": 5,
        "intOption": null,
        "intReviewStar": 0,
        "intReviewVisitor": 0,
        "intUsdCost": 118,
        "strGuideLanguage": "English",
        "strImageUrl": "http://img.kkday.com/image/get/w_1024%2Cc_fit/s1.kkday.com/product_1551/20150525080141_OuZEz/jpg",
        "strIntroduction": "",
        "strLocation": "Italy, Taormina",
        "strOriginUrl": "https://www.kkday.com/en/product/1551",
        "strSource": "KKDAY",
        "strStyle": null,
        "strTitle": "Sicilian Cooking Class in Taormina"
    },
    {
        "intDurationHour": 13,
        "intOption": null,
        "intReviewStar": 0,
        "intReviewVisitor": 0,
        "intUsdCost": 134,
        "strGuideLanguage": "English",
        "strImageUrl": "http://img.kkday.com/image/get/w_1024%2Cc_fit/s1.kkday.com/product_1093/20150525091439_fYVPk/jpg",
        "strIntroduction": "Visit Pompeii, one the world’s most interesting and important archaeological sites, and marvel at the impressive ruins that remain from the devastating eruption of Mount Vesuvius in AD79.",
        "strLocation": "Italy, Rome",
        "strOriginUrl": "https://www.kkday.com/en/product/1093",
        "strSource": "KKDAY",
        "strStyle": null,
        "strTitle": "Trip to Naples and Pompeii"
    },
    {
        "intDurationHour": 5,
        "intOption": null,
        "intReviewStar": 4,
        "intReviewVisitor": 3,
        "intUsdCost": 154,
        "strGuideLanguage": "English,Italiano,Español",
        "strImageUrl": "http://img.kkday.com/image/get/w_1024%2Cc_fit/s1.kkday.com/product_1133/20150525083156_2NtVm/jpg",
        "strIntroduction": "Learn how to cook a four-course Italian meal in a private kitchen in the heart of Rome! You know the saying. When in Rome, do as the Romans do – and the Romans do delicious food. Learn how to cook your own so you can continue eating Italian food long after your vacation ends. In a group of no more than eight people, you’ll receive highly personalized cooking instruction from a knowledgeable food expert, and then enjoy your Italian creations paired with local wine.",
        "strLocation": "Italy, Rome",
        "strOriginUrl": "https://www.kkday.com/en/product/1133",
        "strSource": "KKDAY",
        "strStyle": null,
        "strTitle": "Exclusive cooking lesson"
    },
    {
        "intDurationHour": 4,
        "intOption": null,
        "intReviewStar": 0,
        "intReviewVisitor": 0,
        "intUsdCost": 63,
        "strGuideLanguage": "English",
        "strImageUrl": "http://img.kkday.com/image/get/w_1024%2Cc_fit/s1.kkday.com/product_1111/20160415095336_N6EXr/jpg",
        "strIntroduction": "Eager to be captivated by Angels and Demons? ‘Who were the secret Illuminati’ is a question asked by many who visit the Eternal City, and the official Angels and Demons Tour has the answers! The hidden passageways, riddles at the heart of the city and the ‘hidden secrets’ of the Alter of Science captivate the imagination and curiosity of so many.",
        "strLocation": "Italy, Rome",
        "strOriginUrl": "https://www.kkday.com/en/product/1111",
        "strSource": "KKDAY",
        "strStyle": null,
        "strTitle": "Angels and Demons - The Path of Illumination"
    },
    {
        "intDurationHour": 14,
        "intOption": null,
        "intReviewStar": 0,
        "intReviewVisitor": 0,
        "intUsdCost": 272,
        "strGuideLanguage": "English",
        "strImageUrl": "http://img.kkday.com/image/get/w_1024%2Cc_fit/s1.kkday.com/product_1137/20150525083145_ZXX8q/jpg",
        "strIntroduction": "Semi private Pompeii day tours from Rome , limited to 7 people per van , feature guided walking tours of Pompeii combined with Positano, Amalfi & the scenic Amalfi Coast road.",
        "strLocation": "Italy, Rome",
        "strOriginUrl": "https://www.kkday.com/en/product/1137",
        "strSource": "KKDAY",
        "strStyle": null,
        "strTitle": "Exclusive Rome to Pompeii and Amalfi Coast Trip"
    },
    {
        "intDurationHour": 2,
        "intOption": null,
        "intReviewStar": 5,
        "intReviewVisitor": 1,
        "intUsdCost": 29,
        "strGuideLanguage": "English",
        "strImageUrl": "http://img.kkday.com/image/get/w_1024%2Cc_fit/s1.kkday.com/product_1121/20150525082522_h2mUR/jpg",
        "strIntroduction": "Looking for mystery, intrigue and a reintroduction to the city you thought you knew? The Dark Heart of Rome Tour will stimulate the imagination as much as the eye!",
        "strLocation": "Italy, Rome",
        "strOriginUrl": "https://www.kkday.com/en/product/1121",
        "strSource": "KKDAY",
        "strStyle": null,
        "strTitle": "Dark Heart of Rome"
    },
    {
        "intDurationHour": 7,
        "intOption": null,
        "intReviewStar": 0,
        "intReviewVisitor": 0,
        "intUsdCost": 99,
        "strGuideLanguage": "English",
        "strImageUrl": "http://img.kkday.com/image/get/w_1024%2Cc_fit/s1.kkday.com/product_1173/20160413152724_78oYd/jpg",
        "strIntroduction": "Discover the magic of Florence in a single day on our Florence and Uffizi Gallery walking tour, visiting all of the famous sites and skipping the long lines.",
        "strLocation": "Italy, Florence",
        "strOriginUrl": "https://www.kkday.com/en/product/1173",
        "strSource": "KKDAY",
        "strStyle": null,
        "strTitle": "Best of Florence Tour"
    },
    {
        "intDurationHour": 1,
        "intOption": null,
        "intReviewStar": 0,
        "intReviewVisitor": 0,
        "intUsdCost": 59,
        "strGuideLanguage": "English",
        "strImageUrl": "http://img.kkday.com/image/get/w_1024%2Cc_fit/s1.kkday.com/product_1531/20150525102253_S0WfT/jpg",
        "strIntroduction": "Transfer services are available 24 hours a day, 7 days a week.",
        "strLocation": "Italy, Rome",
        "strOriginUrl": "https://www.kkday.com/en/product/1531",
        "strSource": "KKDAY",
        "strStyle": null,
        "strTitle": "Private Transfer to Fiumicino Airport from Rome or Civitavecchia Port"
    },
    {
        "intDurationHour": 1,
        "intOption": null,
        "intReviewStar": 0,
        "intReviewVisitor": 0,
        "intUsdCost": 77,
        "strGuideLanguage": "English",
        "strImageUrl": "http://img.kkday.com/image/get/w_1024%2Cc_fit/s1.kkday.com/product_1161/20150525080705_DxcMC/jpg",
        "strIntroduction": "Transfer services are available 24 hours a day, 7 days a week.",
        "strLocation": "Italy, Rome",
        "strOriginUrl": "https://www.kkday.com/en/product/1161",
        "strSource": "KKDAY",
        "strStyle": null,
        "strTitle": "Private Transfer from Fiumicino Airport to Rome or Civitavecchia Port"
    },
    {
        "intDurationHour": 2,
        "intOption": null,
        "intReviewStar": 5,
        "intReviewVisitor": 3,
        "intUsdCost": 71,
        "strGuideLanguage": "English",
        "strImageUrl": "http://img.kkday.com/image/get/w_1024%2Cc_fit/s1.kkday.com/product_1127/20150525082740_iO2jk/jpg",
        "strIntroduction": "",
        "strLocation": "Italy, Rome",
        "strOriginUrl": "https://www.kkday.com/en/product/1127",
        "strSource": "KKDAY",
        "strStyle": null,
        "strTitle": "Roman Gladiator School: Learn How to Become a Gladiator"
    },
    {
        "intDurationHour": 1,
        "intOption": null,
        "intReviewStar": 0,
        "intReviewVisitor": 0,
        "intUsdCost": 42,
        "strGuideLanguage": "English",
        "strImageUrl": "http://img.kkday.com/image/get/w_1024%2Cc_fit/s1.kkday.com/product_1192/20160416041046_ZpvPl/jpg",
        "strIntroduction": "Sightsee while you get your exercise on a 1-hour running tour of Rome. Jog by some of The Eternal City’s most popular attractions with a local guide.",
        "strLocation": "Italy, Rome",
        "strOriginUrl": "https://www.kkday.com/en/product/1192",
        "strSource": "KKDAY",
        "strStyle": null,
        "strTitle": "Rome Running Tour"
    },
    {
        "intDurationHour": 1,
        "intOption": null,
        "intReviewStar": 0,
        "intReviewVisitor": 0,
        "intUsdCost": 209,
        "strGuideLanguage": "English",
        "strImageUrl": "http://img.kkday.com/image/get/w_1024%2Cc_fit/s1.kkday.com/product_1185/20150525083513_UU2qm/jpg",
        "strIntroduction": "",
        "strLocation": "Italy, Florence",
        "strOriginUrl": "https://www.kkday.com/en/product/1185",
        "strSource": "KKDAY",
        "strStyle": null,
        "strTitle": "Florence Exclusive Helicopter Tour"
    },
    {
        "intDurationHour": 13,
        "intOption": null,
        "intReviewStar": 5,
        "intReviewVisitor": 1,
        "intUsdCost": 156,
        "strGuideLanguage": "English",
        "strImageUrl": "http://img.kkday.com/image/get/w_1024%2Cc_fit/s1.kkday.com/product_1556/20150525084404_gCwTC/jpg",
        "strIntroduction": "If you are passing through Rome, then don’t miss the chance to visit the picturesque island of Capri on this one day excursion.",
        "strLocation": "Italy, Rome",
        "strOriginUrl": "https://www.kkday.com/en/product/1556",
        "strSource": "KKDAY",
        "strStyle": null,
        "strTitle": "Excursion to Capri Island from Rome"
    },
    {
        "intDurationHour": 2,
        "intOption": null,
        "intReviewStar": 0,
        "intReviewVisitor": 0,
        "intUsdCost": 65,
        "strGuideLanguage": "English",
        "strImageUrl": "http://img.kkday.com/image/get/w_1024%2Cc_fit/s1.kkday.com/product_1144/20150525092019_HngpV/jpg",
        "strIntroduction": "",
        "strLocation": "Italy, Florence",
        "strOriginUrl": "https://www.kkday.com/en/product/1144",
        "strSource": "KKDAY",
        "strStyle": null,
        "strTitle": "Renaissance Court Banquet in Florence"
    }
]